{"data": {"files_attribute_changed": ["C:\\ProgramData\\hzabcojofyn317\\taskdl.exe", "C:\\ProgramData\\hzabcojofyn317\\taskse.exe"], "processes_terminated": ["%CONHOST% \"-464306226-851367519719008150990521842-394017574-959799360411026720-660886838", "%CONHOST% \"15164868772101513324-1996898007853399385880879792103470600-18055639251009404738", "%CONHOST% \"-20834503-7634691791645538042-241691420545465520-2088001280-279374024-2102624805", "cmd.exe /c \"%ProgramData%\\yuuaclhph815\\tasksche.exe\"", "attrib +h +s Z:\\$RECYCLE", "taskdl.exe", "icacls . /grant Everyone:F /T /C /Q", "attrib +h +s D:\\$RECYCLE", "attrib +h .", "cscript.exe  //nologo m.vbs", "%SAMPLEPATH%", "%windir%\\tasksche.exe /i", "%SAMPLEPATH% -m security", "lhdfrgui.exe", "C:\\WINDOWS\\tasksche.exe /i", "2300 - C:\\Users\\admin\\Downloads\\lhdfrgui.exe -m security", "2432 - C:\\WINDOWS\\tasksche.exe /i", "2516 - cmd.exe /c \"C:\\ProgramData\\hzabcojofyn317\\tasksche.exe\"", "2528 - C:\\ProgramData\\hzabcojofyn317\\tasksche.exe", "2596 - icacls . /grant Everyone:F /T /C /Q", "2712 - taskdl.exe", "2740 - C:\\Windows\\system32\\cmd.exe /c 170801627321454.bat", "2772 - cscript.exe  //nologo m.vbs"], "memory_pattern_domains": ["cwwnhwhlz52maqm7.onion", "gx7ekbenv2riucmf.onion", "57g7spgrzlojinas.onion", "xxlvbrloxvriy2c5.onion", "76jdd2ir2embyv47.onion", "www.ifferfsodp9ifjaposdfjhgosurijfaewrwergwea.com"], "processes_created": ["C:\\WINDOWS\\tasksche.exe /i"], "files_opened": ["C:\\Users\\<USER>\\AppData\\Local\\Microsoft\\Windows\\Temporary Internet Files", "C:\\Windows\\system32\\api-ms-win-downlevel-advapi32-l2-1-0.dll", "C:\\Users\\<USER>\\AppData\\Local\\Microsoft\\Windows\\Temporary Internet Files\\counters.dat", "C:\\Windows\\system32\\winhttp.dll", "C:\\Windows\\system32\\webio.dll", "C:\\Windows\\system32\\mswsock.dll", "C:\\Windows\\system32\\api-ms-win-downlevel-shlwapi-l2-1-0.dll", "C:\\Windows\\System32\\wship6.dll", "\\Device\\Afd\\Endpoint", "C:\\Windows\\system32\\dhcpcsvc6.DLL", "C:\\Windows\\System32\\wshtcpip.dll", "C:\\Users\\admin", "C:\\Users\\<USER>\\AppData\\Local", "C:\\Users\\<USER>\\AppData\\Local\\Microsoft\\Windows\\Temporary Internet Files\\Content.IE5", "C:\\Windows\\system32\\dhcpcsvc.DLL", "C:\\Users\\<USER>\\AppData\\Roaming", "C:\\Users\\<USER>\\AppData\\Roaming\\Microsoft\\Windows\\Cookies", "C:\\Users\\<USER>\\AppData\\Local\\Microsoft\\Windows\\History", "C:\\Users\\<USER>\\AppData\\Local\\Microsoft\\Windows\\History\\History.IE5", "C:\\Windows\\system32\\rasadhlp.dll", "\\Device\\RasAcd", "\\DEVICE\\NETBT_TCPIP_{F0C53D6E-70E2-4027-95D3-23510DC2383A}", "C:\\Windows\\System32\\netprofm.dll", "\\DEVICE\\NETBT_TCPIP_{846EE342-7039-11DE-9D20-806E6F6E6963}", "\\DEVICE\\NETBT_TCPIP_{83811ED5-13C8-4FB1-B6A3-6B9E83E6B1EE}", "C:\\Windows\\System32\\nlaapi.dll", "C:\\Windows\\system32\\CRYPTSP.dll", "C:\\Windows\\system32\\rsaenh.dll", "C:\\Windows\\system32\\RpcRtRemote.dll", "\\Device\\NetBT_Tcpip_{F0C53D6E-70E2-4027-95D3-23510DC2383A}", "\\Device\\NetBT_Tcpip_{E698D55B-6E63-4B2F-ABDF-E08FDA424715}", "\\Device\\NetBT_Tcpip6_{F0C53D6E-70E2-4027-95D3-23510DC2383A}", "\\Device\\NetBT_Tcpip6_{83811ED5-13C8-4FB1-B6A3-6B9E83E6B1EE}", "\\Device\\NetBT_Tcpip6_{E698D55B-6E63-4B2F-ABDF-E08FDA424715}", "C:\\Windows\\System32\\npmproxy.dll", "C:\\WINDOWS\\tasksche.exe", "C:\\Windows\\system32\\apphelp.dll", "\\SystemRoot\\AppPatch\\sysmain.sdb", "C:\\ProgramData", "hzabcojofyn317", "C:\\ProgramData\\hzabcojofyn317", "C:\\ProgramData\\hzabcojofyn317\\tasksche.exe"], "registry_keys_set": [{"key": "HKLM\\Software\\Microsoft\\WBEM\\WDM\\%windir%\\system32\\drivers\\ndis.sys[MofResourceName]", "value": "LowDateTime:-331231481,HighDateTime:30676316***Binary mof failed, see WMIPROV.LOG"}, {"key": "HKLM\\Software\\Microsoft\\WBEM\\WDM\\%windir%\\System32\\Drivers\\portcls.SYS[PortclsMof]", "value": "LowDateTime:418629328,HighDateTime:30487037***Binary mof compiled successfully"}, {"key": "HKLM\\Software\\Microsoft\\WBEM\\WDM\\%windir%\\system32\\drivers\\en-US\\ACPI.sys.mui[ACPIMOFResource]", "value": "LowDateTime:1237199616,HighDateTime:30016579***Binary mof compiled successfully"}, {"key": "HKLM\\Software\\Microsoft\\WBEM\\WDM\\%windir%\\system32\\DRIVERS\\HDAudBus.sys[HDAudioMofName]", "value": "LowDateTime:-227274444,HighDateTime:30116024***Binary mof compiled successfully"}, {"key": "HKLM\\Software\\Microsoft\\WBEM\\WDM\\%windir%\\System32\\Drivers\\en-US\\portcls.SYS.mui[PortclsMof]", "value": "LowDateTime:1137199616,HighDateTime:30016579***Binary mof compiled successfully"}, {"key": "HKLM\\Software\\Microsoft\\WBEM\\WDM\\%windir%\\system32\\advapi32.dll[MofResourceName]", "value": "LowDateTime:302488720,HighDateTime:30778805***Binary mof compiled successfully"}, {"key": "HKLM\\Software\\Microsoft\\WBEM\\WDM\\%windir%\\system32\\en-US\\advapi32.dll.mui[MofResourceName]", "value": "LowDateTime:369951187,HighDateTime:30778805***Binary mof compiled successfully"}, {"key": "HKLM\\Software\\Microsoft\\WBEM\\WDM\\%windir%\\system32\\drivers\\en-US\\mssmbios.sys.mui[MofResource]", "value": "LowDateTime:1497199616,HighDateTime:30016579***Binary mof compiled successfully"}, {"key": "HKLM\\Software\\Microsoft\\WBEM\\WDM\\%windir%\\system32\\DRIVERS\\en-US\\HDAudBus.sys.mui[HDAudioMofName]", "value": "LowDateTime:-377767680,HighDateTime:30016579***Binary mof compiled successfully"}, {"key": "HKLM\\Software\\Microsoft\\WBEM\\WDM\\%windir%\\system32\\drivers\\en-US\\ndis.sys.mui[MofResourceName]", "value": "LowDateTime:382232320,HighDateTime:30016580***Binary mof failed, see WMIPROV.LOG"}, {"key": "HKLM\\Software\\Microsoft\\WBEM\\WDM\\%windir%\\system32\\DRIVERS\\en-US\\intelppm.sys.mui[PROCESSORWMI]", "value": "LowDateTime:-577767680,HighDateTime:30016579***Binary mof compiled successfully"}, {"key": "HKLM\\Software\\Microsoft\\WBEM\\WDM\\IDE\\DiskAMDX_HARDDISK___________________________2.5+____\\5&2770a7af&0&0.0.0_0-{05901221-D566-11d1-B2F0-00A0C9062910}", "value": "LowDateTime:803713417,HighDateTime:0***Binary mof compiled successfully"}, {"key": "HKLM\\Software\\Microsoft\\WBEM\\WDM\\%windir%\\system32\\DRIVERS\\intelppm.sys[PROCESSORWMI]", "value": "LowDateTime:-445445610,HighDateTime:30778799***Binary mof compiled successfully"}, {"key": "HKLM\\Software\\Microsoft\\WBEM\\WDM\\%windir%\\system32\\drivers\\ACPI.sys[ACPIMOFResource]", "value": "LowDateTime:398767260,HighDateTime:30646967***Binary mof compiled successfully"}, {"key": "HKLM\\Software\\Microsoft\\WBEM\\WDM\\%windir%\\system32\\DRIVERS\\monitor.sys[MonitorWMI]", "value": "LowDateTime:-1637837527,HighDateTime:30762899***Binary mof failed, see WMIPROV.LOG"}, {"key": "HKLM\\Software\\Microsoft\\WBEM\\WDM\\%windir%\\system32\\drivers\\mssmbios.sys[MofResource]", "value": "LowDateTime:-649833737,HighDateTime:30733938***Binary mof compiled successfully"}, {"key": "HKU\\S-1-5-18\\Software\\Microsoft\\Windows\\CurrentVersion\\Internet Settings\\5.0\\Cache\\Cookies\\CachePrefix", "value": "Cookie:"}, {"key": "\\\\REGISTRY\\A\\{c4363633-9e8a-11ea-ae26-167c9a143b2e}\\DefaultObjectStore\\LruList\\0000000000002B6A\\ObjectLru"}, {"key": "\\\\REGISTRY\\A\\{c4363633-9e8a-11ea-ae26-167c9a143b2e}\\DefaultObjectStore\\LruList\\0000000000002B6A\\ObjectId"}, {"key": "\\\\REGISTRY\\A\\{c4363633-9e8a-11ea-ae26-167c9a143b2e}\\DefaultObjectStore\\ObjectTable\\664\\_FileId_"}, {"key": "\\\\REGISTRY\\A\\{c4363633-9e8a-11ea-ae26-167c9a143b2e}\\DefaultObjectStore\\ObjectTable\\664\\_ObjectLru_"}, {"key": "\\\\REGISTRY\\A\\{c4363633-9e8a-11ea-ae26-167c9a143b2e}\\DefaultObjectStore\\ObjectTable\\664\\_Usn_"}, {"key": "\\\\REGISTRY\\A\\{c4363633-9e8a-11ea-ae26-167c9a143b2e}\\DefaultObjectStore\\ObjectTable\\664\\_ObjectId_"}, {"key": "\\\\REGISTRY\\A\\{c4363633-9e8a-11ea-ae26-167c9a143b2e}\\DefaultObjectStore\\ObjectTable\\664\\AeFileID"}, {"key": "\\\\REGISTRY\\A\\{c4363633-9e8a-11ea-ae26-167c9a143b2e}\\DefaultObjectStore\\ObjectTable\\664\\_UsnJournalId_"}, {"key": "\\\\REGISTRY\\A\\{c4363633-9e8a-11ea-ae26-167c9a143b2e}\\DefaultObjectStore\\ObjectTable\\664\\AeProgramID"}, {"key": "\\\\REGISTRY\\A\\{c4363633-9e8a-11ea-ae26-167c9a143b2e}\\DefaultObjectStore\\LruList\\0000000000002B6D\\ObjectLru"}, {"key": "\\\\REGISTRY\\A\\{c4363633-9e8a-11ea-ae26-167c9a143b2e}\\DefaultObjectStore\\LruList\\0000000000002B6D\\ObjectId"}, {"key": "HKU\\S-1-5-21-575823232-3065301323-1442773979-1000\\Software\\Microsoft\\Windows\\CurrentVersion\\Internet Settings\\5.0\\Cache\\Content\\CachePrefix"}, {"key": "\\\\REGISTRY\\A\\{c4363633-9e8a-11ea-ae26-167c9a143b2e}\\DefaultObjectStore\\ObjectTable\\663\\_FileId_"}, {"key": "\\\\REGISTRY\\A\\{c4363633-9e8a-11ea-ae26-167c9a143b2e}\\DefaultObjectStore\\ObjectTable\\663\\_ObjectLru_"}, {"key": "\\\\REGISTRY\\A\\{c4363633-9e8a-11ea-ae26-167c9a143b2e}\\DefaultObjectStore\\ObjectTable\\663\\_Usn_"}, {"key": "\\\\REGISTRY\\A\\{c4363633-9e8a-11ea-ae26-167c9a143b2e}\\DefaultObjectStore\\ObjectTable\\663\\_ObjectId_"}, {"key": "\\\\REGISTRY\\A\\{c4363633-9e8a-11ea-ae26-167c9a143b2e}\\DefaultObjectStore\\ObjectTable\\663\\AeFileID"}, {"key": "\\\\REGISTRY\\A\\{c4363633-9e8a-11ea-ae26-167c9a143b2e}\\DefaultObjectStore\\ObjectTable\\663\\_UsnJournalId_"}, {"key": "\\\\REGISTRY\\A\\{c4363633-9e8a-11ea-ae26-167c9a143b2e}\\DefaultObjectStore\\ObjectTable\\663\\AeProgramID"}, {"key": "HKLM\\SYSTEM\\ControlSet001\\Control\\Session Manager\\PendingFileRenameOperations", "value": "\\??\\%HOME%\\Desktop\\My credit cards.xlsx\n\n\\??\\%HOME%\\Desktop\\My documents.docx\n\n\\??\\%HOME%\\Desktop\\New PT.pptx\n\n\\??\\%HOME%\\Desktop\\Payment plans.docx\n\n\\??\\%HOME%\\Desktop\\Salaries.xlsx\n\n\\??\\%HOME%\\Desktop\\Taxes.xlsx\n\n\\??\\%HOME%\\Documents\\OneNote Notebooks\\Personal\\Open Notebook.onetoc2\n\n\\??\\%HOME%\\Documents\\Outlook Files\\leonid.pidorovich@gmx.de.pst\n\n\\??\\%WORKDIR%\\stderr.txt\n\n\\??\\%WORKDIR%\\stdout.txt\n\n\\??\\C:\\PC\\LICENSE.txt\n\n\\??\\C:\\PC\\NEWS.txt\n\n\\??\\C:\\PC\\README.txt\n\n\\??\\C:\\PC\\Lib\\idlelib\\idle_test\\README.txt\n\n\\??\\C:\\PC\\Lib\\lib2to3\\Grammar.txt\n\n\\??\\C:\\PC\\Lib\\site-packages\\adodbapi\\license.txt\n\n\\??\\C:\\PC\\Lib\\site-packages\\adodbapi\\readme.txt\n\n\\??\\C:\\PC\\Lib\\site-packages\\pip-19.2.3.dist-info\\LICENSE.txt\n\n\\??\\C:\\PC\\Lib\\site-packages\\pythonwin\\license.txt\n\n\\??\\C:\\PC\\Lib\\site-packages\\pywin32-227.dist-info\\top_level.txt\n\n\\??\\C:\\PC\\Lib\\site-packages\\setuptools-41.2.0.dist-info\\entry_points.txt\n\n\\??\\C:\\PC\\Lib\\site-packages\\urllib3-1.25.7.dist-info\\LICENSE.txt\n\n\\??\\C:\\PC\\Lib\\site-packages\\win32\\license.txt\n\n\\??\\C:\\PC\\Lib"}, {"key": "HKU\\S-1-5-18\\Software\\Microsoft\\Windows\\CurrentVersion\\Internet Settings\\ZoneMap\\\\AutoDetect", "value": "1"}, {"key": "HKU\\S-1-5-18\\Software\\Microsoft\\Windows\\CurrentVersion\\Internet Settings\\ZoneMap\\\\UNCAsIntranet", "value": "0"}, {"key": "HKLM\\SYSTEM\\ControlSet001\\Control\\Network\\{4D36E972-E325-11CE-BFC1-08002BE10318}\\{B5DA8633-954C-4495-AE46-0BB5B5FB1CDC}\\Connection\\PnpInstanceID", "value": "PCI\\VEN_8086&DEV_100E&SUBSYS_11001AF4&REV_03\\3&13C0B0C5&0&90"}, {"key": "HKU\\S-1-5-21-575823232-3065301323-1442773979-1000\\Software\\Microsoft\\Windows\\CurrentVersion\\Internet Settings\\ProxyServer", "value": "%HTTP_PROXY%:8080"}, {"key": "HKU\\S-1-5-21-575823232-3065301323-1442773979-1000\\Software\\Microsoft\\Windows\\CurrentVersion\\Internet Settings\\ProxyEnable", "value": "1"}, {"key": "HKLM\\SYSTEM\\ControlSet001\\Services\\BITS\\Performance\\PerfMMFileName", "value": "Global\\MMF_BITS_s"}, {"key": "HKU\\S-1-5-18\\Software\\Microsoft\\Windows\\CurrentVersion\\Internet Settings\\5.0\\Cache\\History\\CachePrefix", "value": "Visited:"}, {"key": "HKU\\S-1-5-18\\Software\\Microsoft\\Windows\\CurrentVersion\\Internet Settings\\5.0\\Cache\\Content\\CachePrefix"}, {"key": "HKLM\\SYSTEM\\ControlSet001\\Services\\Tcpip\\Parameters\\DhcpDomain", "value": "sales.local"}, {"key": "HKLM\\SYSTEM\\ControlSet001\\Services\\Tcpip\\Parameters\\DhcpNameServer", "value": "%GATEWAY%"}, {"key": "HKLM\\SYSTEM\\ControlSet001\\Services\\MpsSvc\\Parameters\\PortKeywords\\DHCP\\Collection"}, {"key": "HKU\\S-1-5-18\\Software\\Microsoft\\Windows\\CurrentVersion\\Internet Settings\\Wpad\\{81DD9794-74E0-440F-AF7E-F10E5AC81618}\\WpadDecisionTime", "value": "40 66 A9 21 98 32 D6 01"}, {"key": "HKU\\S-1-5-18\\Software\\Microsoft\\Windows\\CurrentVersion\\Internet Settings\\Wpad\\{81DD9794-74E0-440F-AF7E-F10E5AC81618}\\WpadDecision", "value": "0"}, {"key": "HKU\\S-1-5-18\\Software\\Microsoft\\Windows\\CurrentVersion\\Internet Settings\\Wpad\\{81DD9794-74E0-440F-AF7E-F10E5AC81618}\\WpadDecisionReason", "value": "2"}, {"key": "HKU\\S-1-5-18\\Software\\Microsoft\\Windows\\CurrentVersion\\Internet Settings\\Wpad\\{81DD9794-74E0-440F-AF7E-F10E5AC81618}\\WpadNetworkName", "value": "Network  5"}, {"key": "\\\\REGISTRY\\A\\{c4363633-9e8a-11ea-ae26-167c9a143b2e}\\DefaultObjectStore\\LruList\\CurrentLru"}, {"key": "HKLM\\SYSTEM\\ControlSet001\\Control\\DeviceClasses\\{ad498944-762f-11d0-8dcb-00c04fc3358c}\\##?#SW#{eeab7790-c514-11d1-b42b-00805fc1270e}#asyncmac#{ad498944-762f-11d0-8dcb-00c04fc3358c}\\#{78032B7E-4968-42D3-9F37-287EA86C0AAA}\\SymbolicLink", "value": "\\\\?\\SW#{eeab7790-c514-11d1-b42b-00805fc1270e}#asyncmac#{ad498944-762f-11d0-8dcb-00c04fc3358c}\\{78032B7E-4968-42D3-9F37-287EA86C0AAA}"}, {"key": "HKLM\\Software\\Microsoft\\WBEM\\CIMOM\\ConfigValueEssNeedsLoading", "value": "1"}, {"key": "HKLM\\Software\\Microsoft\\WBEM\\CIMOM\\List of event-active namespaces", "value": "00 00 54 00 45 00 76 00 65 00 6E 00 74 00 4C 00 6F 00 67 00 45 00 76 00 65 00 6E 00 74 00 43 00 6F 00 6E 00 73 00 75 00 6D 00 65 00 72 00"}, {"key": "HKU\\S-1-5-18\\Software\\Microsoft\\Windows\\CurrentVersion\\Internet Settings\\Connections\\SavedLegacySettings", "value": "46 00 00 00 10 00 00 00 09 00 00 00 00 00 00 00 00 00 00 00 00 00 00 00 04 00 00 00 00 00 00 00 90 6F 5C 15 D2 C1 D5 01 00 00 00 00 00 00 00 00 00 00 00 00 02 00 00 00 17 00 00 00 00 00 00 00 00 00 00 00 00 00 00 00 00 00 00 00 00 00 00 01 00 00 00 00 00 00 00 00 D0 5C 32 00 00 00 00 00 D0 5C 32 00 00 00 00 00 00 00 00 00 00 00 00 00 00 00 00 00 00 00 00 00 F0 5C 32 00 00 00 00 00 F0 5C 32 00 00 00 00 00 70 5B 32 00 00 00 00 00 00 00 00 00 00 00 00 00 00 00 00 00 00 00 00 00 84 02 00 00 00 00 00 00 00 00 00 00 00 00 00 00 2A 00 00 2A DD 9B 00 00 02 00 00 00 C0 A8 7D 02 00 00 00 00 00 00 00 00 00 00 00 00 00 00 00 00 00 00 00 00 00 00 00 00 00 00 00 00 00 00 00 00 00 00 00 00 00 00 00 00 00 00 00 00 00 00 00 00 00 00 00 00 00 00 00 00 00 00 00 00 00 00 00 00 00 00 00 00 00 00 00 00 00 00 00 00 00 00 00 00 00 00 00 00 00 00 00 00 00 00 00 00 00 00 00 00 00 00 00 00 00 00 00 00 01 00 00 00 00 00 00 00 C0 5D 32 00 00 00 00 00"}, {"key": "HKU\\S-1-5-18\\Software\\Microsoft\\Windows\\CurrentVersion\\Internet Settings\\Connections\\DefaultConnectionSettings", "value": "46 00 00 00 03 00 00 00 09 00 00 00 00 00 00 00 00 00 00 00 00 00 00 00 04 00 00 00 00 00 00 00 90 6F 5C 15 D2 C1 D5 01 00 00 00 00 00 00 00 00 00 00 00 00 01 00 00 00 02 00 00 00 C0 A8 7D 30 00 00 00 00 00 00 00 00 00 00 00 00 00 00 00 00 00 00 00 00 00 00 00 00 00 00 00 00 00 00 00 00 00 00 00 00 00 00 00 00 00 00 00 00 00 00 00 00 00 00 00 00 00 00 00 00 00 00 00 00 00 00 00 00 00 00 00 00 00 00 00 00 00 00 00 00 00 00 00 00 00 00 00 00 00 00 00 00 00 00 00 00 00 00 00 00 00 00 00 00 00 00 00 00 00 00 00 00 00 00 00 00 00 00 00 00 00 00 00 00"}, {"key": "\\\\REGISTRY\\A\\{c4363633-9e8a-11ea-ae26-167c9a143b2e}\\DefaultObjectStore\\ObjectTable\\667\\Indexes\\FileIdIndex-{853201e6-2d75-11ea-a138-806e6f6e6963}\\1000000039923"}, {"key": "HKLM\\SYSTEM\\ControlSet001\\Control\\BackupRestore\\FilesNotToBackup\\BITS_LOG", "value": "%windir%\\System32\\Bits.log\n"}, {"key": "HKLM\\SYSTEM\\ControlSet001\\Control\\BackupRestore\\FilesNotToBackup\\BITS_BAK", "value": "%windir%\\System32\\Bits.bak\n"}, {"key": "\\\\REGISTRY\\A\\{c4363633-9e8a-11ea-ae26-167c9a143b2e}\\DefaultObjectStore\\LruList\\0000000000002B76\\ObjectLru"}, {"key": "\\\\REGISTRY\\A\\{c4363633-9e8a-11ea-ae26-167c9a143b2e}\\DefaultObjectStore\\LruList\\0000000000002B76\\ObjectId"}, {"key": "\\\\REGISTRY\\A\\{c4363633-9e8a-11ea-ae26-167c9a143b2e}\\DefaultObjectStore\\IndexTable\\FileIdIndex-{853201e6-2d75-11ea-a138-806e6f6e6963}\\1000000039923\\667"}, {"key": "HKLM\\SYSTEM\\ControlSet001\\Services\\WmiApRpl\\Performance\\Last Counter", "value": "12642"}, {"key": "HKLM\\SYSTEM\\ControlSet001\\Services\\WmiApRpl\\Performance\\Object List", "value": "12476 12482 12492 12502 12522 12566 12576 12614 12620 12636"}, {"key": "HKLM\\SYSTEM\\ControlSet001\\Services\\WmiApRpl\\Performance\\Last Help", "value": "12643"}, {"key": "HKLM\\SYSTEM\\ControlSet001\\Services\\WmiApRpl\\Performance\\First Counter", "value": "12476"}, {"key": "HKLM\\SYSTEM\\ControlSet001\\Services\\WmiApRpl\\Performance\\First Help", "value": "12477"}, {"key": "HKLM\\SYSTEM\\ControlSet001\\Services\\WmiApRpl\\Performance\\PerfIniFile", "value": "WmiApRpl.ini\u0000\u0000\u0000\u0000\u0000\u0000\u0000\u0000\u0000\u0000\u0000\u0000\u0000\u0000\u0000\u0000\u0000\u0000\u0000\u0000\u0000\u0000\u0000\u0000\u0000\u0000\u0000\u0000\u0000\u0000\u0000\u0000\u0000\u0000\u0000\u0000"}, {"key": "HKLM\\SYSTEM\\ControlSet001\\Control\\DeviceClasses\\{cac88484-7515-4c03-82e6-71a87abac361}\\##?#SW#{eeab7790-c514-11d1-b42b-00805fc1270e}#asyncmac#{cac88484-7515-4c03-82e6-71a87abac361}\\DeviceInstance", "value": "SW\\{eeab7790-c514-11d1-b42b-00805fc1270e}\\asyncmac"}, {"key": "\\\\REGISTRY\\A\\{c4363633-9e8a-11ea-ae26-167c9a143b2e}\\DefaultObjectStore\\ObjectTable\\662\\_FileId_"}, {"key": "\\\\REGISTRY\\A\\{c4363633-9e8a-11ea-ae26-167c9a143b2e}\\DefaultObjectStore\\ObjectTable\\662\\_ObjectLru_"}, {"key": "\\\\REGISTRY\\A\\{c4363633-9e8a-11ea-ae26-167c9a143b2e}\\DefaultObjectStore\\ObjectTable\\662\\_Usn_"}, {"key": "\\\\REGISTRY\\A\\{c4363633-9e8a-11ea-ae26-167c9a143b2e}\\DefaultObjectStore\\ObjectTable\\662\\_ObjectId_"}, {"key": "\\\\REGISTRY\\A\\{c4363633-9e8a-11ea-ae26-167c9a143b2e}\\DefaultObjectStore\\ObjectTable\\662\\AeFileID"}, {"key": "\\\\REGISTRY\\A\\{c4363633-9e8a-11ea-ae26-167c9a143b2e}\\DefaultObjectStore\\ObjectTable\\662\\_UsnJournalId_"}, {"key": "\\\\REGISTRY\\A\\{c4363633-9e8a-11ea-ae26-167c9a143b2e}\\DefaultObjectStore\\ObjectTable\\662\\AeProgramID"}, {"key": "\\\\REGISTRY\\A\\{c4363633-9e8a-11ea-ae26-167c9a143b2e}\\DefaultObjectStore\\_CurrentObjectId_"}, {"key": "\\\\REGISTRY\\A\\{c4363633-9e8a-11ea-ae26-167c9a143b2e}\\DefaultObjectStore\\LruList\\0000000000002B70\\ObjectLru"}, {"key": "\\\\REGISTRY\\A\\{c4363633-9e8a-11ea-ae26-167c9a143b2e}\\DefaultObjectStore\\LruList\\0000000000002B70\\ObjectId"}, {"key": "\\\\REGISTRY\\A\\{c4363633-9e8a-11ea-ae26-167c9a143b2e}\\DefaultObjectStore\\ObjectTable\\661\\_FileId_"}, {"key": "\\\\REGISTRY\\A\\{c4363633-9e8a-11ea-ae26-167c9a143b2e}\\DefaultObjectStore\\ObjectTable\\661\\_ObjectLru_"}, {"key": "\\\\REGISTRY\\A\\{c4363633-9e8a-11ea-ae26-167c9a143b2e}\\DefaultObjectStore\\ObjectTable\\661\\_Usn_"}, {"key": "\\\\REGISTRY\\A\\{c4363633-9e8a-11ea-ae26-167c9a143b2e}\\DefaultObjectStore\\ObjectTable\\661\\_ObjectId_"}, {"key": "\\\\REGISTRY\\A\\{c4363633-9e8a-11ea-ae26-167c9a143b2e}\\DefaultObjectStore\\ObjectTable\\661\\AeFileID"}, {"key": "\\\\REGISTRY\\A\\{c4363633-9e8a-11ea-ae26-167c9a143b2e}\\DefaultObjectStore\\ObjectTable\\661\\_UsnJournalId_"}, {"key": "\\\\REGISTRY\\A\\{c4363633-9e8a-11ea-ae26-167c9a143b2e}\\DefaultObjectStore\\ObjectTable\\661\\AeProgramID"}, {"key": "HKLM\\SYSTEM\\ControlSet001\\Control\\DeviceClasses\\{ad498944-762f-11d0-8dcb-00c04fc3358c}\\##?#SW#{eeab7790-c514-11d1-b42b-00805fc1270e}#asyncmac#{ad498944-762f-11d0-8dcb-00c04fc3358c}\\Control\\ReferenceCount", "value": "1"}, {"key": "\\\\REGISTRY\\A\\{c4363633-9e8a-11ea-ae26-167c9a143b2e}\\DefaultObjectStore\\IndexTable\\FileIdIndex-{853201e6-2d75-11ea-a138-806e6f6e6963}\\1000000009285\\664"}, {"key": "\\\\REGISTRY\\A\\{c4363633-9e8a-11ea-ae26-167c9a143b2e}\\DefaultObjectStore\\ObjectTable\\664\\Indexes\\FileIdIndex-{853201e6-2d75-11ea-a138-806e6f6e6963}\\1000000009285"}, {"key": "HKLM\\SYSTEM\\ControlSet001\\Control\\DeviceClasses\\{ad498944-762f-11d0-8dcb-00c04fc3358c}\\##?#SW#{eeab7790-c514-11d1-b42b-00805fc1270e}#asyncmac#{ad498944-762f-11d0-8dcb-00c04fc3358c}\\#{78032B7E-4968-42D3-9F37-287EA86C0AAA}\\Control\\Linked", "value": "1"}, {"key": "\\\\REGISTRY\\A\\{c4363633-9e8a-11ea-ae26-167c9a143b2e}\\DefaultObjectStore\\IndexTable\\FileIdIndex-{853201e6-2d75-11ea-a138-806e6f6e6963}\\6000000009A6F\\665"}, {"key": "HKU\\S-1-5-21-575823232-3065301323-1442773979-1000\\Software\\Microsoft\\Windows\\CurrentVersion\\Internet Settings\\ZoneMap\\\\AutoDetect", "value": "1"}, {"key": "HKU\\S-1-5-21-575823232-3065301323-1442773979-1000\\Software\\Microsoft\\Windows\\CurrentVersion\\Internet Settings\\ZoneMap\\\\UNCAsIntranet", "value": "0"}, {"key": "\\\\REGISTRY\\A\\{c4363633-9e8a-11ea-ae26-167c9a143b2e}\\DefaultObjectStore\\ObjectTable\\666\\Indexes\\FileIdIndex-{853201e6-2d75-11ea-a138-806e6f6e6963}\\4000000009AC4"}, {"key": "\\\\REGISTRY\\A\\{c4363633-9e8a-11ea-ae26-167c9a143b2e}\\DefaultObjectStore\\LruList\\0000000000002B73\\ObjectLru"}, {"key": "\\\\REGISTRY\\A\\{c4363633-9e8a-11ea-ae26-167c9a143b2e}\\DefaultObjectStore\\LruList\\0000000000002B73\\ObjectId"}, {"key": "HKU\\S-1-5-18\\Software\\Microsoft\\Windows Script\\Settings\\JITDebug", "value": "0"}, {"key": "\\\\REGISTRY\\A\\{c4363633-9e8a-11ea-ae26-167c9a143b2e}\\DefaultObjectStore\\ObjectTable\\663\\Indexes\\FileIdIndex-{853201e6-2d75-11ea-a138-806e6f6e6963}\\1000000009069"}, {"key": "HKLM\\SYSTEM\\ControlSet001\\Control\\DeviceClasses\\{cac88484-7515-4c03-82e6-71a87abac361}\\##?#SW#{eeab7790-c514-11d1-b42b-00805fc1270e}#asyncmac#{cac88484-7515-4c03-82e6-71a87abac361}\\#\\Control\\Linked", "value": "1"}, {"key": "HKLM\\SYSTEM\\ControlSet001\\Services\\Tcpip\\Parameters\\Interfaces\\{b5da8633-954c-4495-ae46-0bb5b5fb1cdc}\\DhcpDefaultGateway", "value": "%GATEWAY%\n"}, {"key": "HKLM\\SYSTEM\\ControlSet001\\Services\\Tcpip\\Parameters\\Interfaces\\{b5da8633-954c-4495-ae46-0bb5b5fb1cdc}\\DhcpDomain", "value": "sales.local"}, {"key": "HKLM\\SYSTEM\\ControlSet001\\Services\\Tcpip\\Parameters\\Interfaces\\{b5da8633-954c-4495-ae46-0bb5b5fb1cdc}\\DhcpSubnetMaskOpt", "value": "255.255.255.0\n"}, {"key": "HKLM\\SYSTEM\\ControlSet001\\Services\\Tcpip\\Parameters\\Interfaces\\{b5da8633-954c-4495-ae46-0bb5b5fb1cdc}\\DhcpNameServer", "value": "%GATEWAY%"}, {"key": "\\\\REGISTRY\\A\\{c4363633-9e8a-11ea-ae26-167c9a143b2e}\\DefaultObjectStore\\IndexTable\\FileIdIndex-{853201e6-2d75-11ea-a138-806e6f6e6963}\\2F00000000061F\\662"}, {"key": "HKLM\\Software\\Wow6432Node\\WanaCrypt0r\\wd", "value": "%ProgramData%\\yuuaclhph815"}, {"key": "\\\\REGISTRY\\A\\{c4363633-9e8a-11ea-ae26-167c9a143b2e}\\DefaultObjectStore\\IndexTable\\FileIdIndex-{853201e6-2d75-11ea-a138-806e6f6e6963}\\4000000009AC4\\666"}, {"key": "HKLM\\SYSTEM\\ControlSet001\\Control\\DeviceClasses\\{cac88484-7515-4c03-82e6-71a87abac361}\\##?#SW#{eeab7790-c514-11d1-b42b-00805fc1270e}#asyncmac#{cac88484-7515-4c03-82e6-71a87abac361}\\#\\SymbolicLink", "value": "\\\\?\\SW#{eeab7790-c514-11d1-b42b-00805fc1270e}#asyncmac#{cac88484-7515-4c03-82e6-71a87abac361}"}, {"key": "\\\\REGISTRY\\A\\{c4363633-9e8a-11ea-ae26-167c9a143b2e}\\DefaultObjectStore\\ObjectTable\\662\\Indexes\\FileIdIndex-{853201e6-2d75-11ea-a138-806e6f6e6963}\\2F00000000061F"}, {"key": "\\\\REGISTRY\\A\\{c4363633-9e8a-11ea-ae26-167c9a143b2e}\\DefaultObjectStore\\ObjectTable\\665\\_FileId_"}, {"key": "\\\\REGISTRY\\A\\{c4363633-9e8a-11ea-ae26-167c9a143b2e}\\DefaultObjectStore\\ObjectTable\\665\\_ObjectLru_"}, {"key": "\\\\REGISTRY\\A\\{c4363633-9e8a-11ea-ae26-167c9a143b2e}\\DefaultObjectStore\\ObjectTable\\665\\_Usn_"}, {"key": "\\\\REGISTRY\\A\\{c4363633-9e8a-11ea-ae26-167c9a143b2e}\\DefaultObjectStore\\ObjectTable\\665\\_ObjectId_"}, {"key": "\\\\REGISTRY\\A\\{c4363633-9e8a-11ea-ae26-167c9a143b2e}\\DefaultObjectStore\\ObjectTable\\665\\AeFileID"}, {"key": "\\\\REGISTRY\\A\\{c4363633-9e8a-11ea-ae26-167c9a143b2e}\\DefaultObjectStore\\ObjectTable\\665\\_UsnJournalId_"}, {"key": "\\\\REGISTRY\\A\\{c4363633-9e8a-11ea-ae26-167c9a143b2e}\\DefaultObjectStore\\ObjectTable\\665\\AeProgramID"}, {"key": "HKU\\S-1-5-21-575823232-3065301323-1442773979-1000\\Software\\Microsoft\\Windows\\CurrentVersion\\Internet Settings\\Connections\\SavedLegacySettings", "value": "46 00 00 00 04 01 00 00 03 00 00 00 14 00 00 00 65 78 74 72 61 63 74 6F 72 2E 70 72 6F 78 79 3A 38 30 38 30 00 00 00 00 00 00 00 00 00 00 00 00 00 00 00 00 00 D0 5C 01 4D C1 D5 01 00 00 00 00 00 00 00 00 00 00 00 00 00 00 00 00"}, {"key": "\\\\REGISTRY\\A\\{c4363633-9e8a-11ea-ae26-167c9a143b2e}\\DefaultObjectStore\\IndexTable\\FileIdIndex-{853201e6-2d75-11ea-a138-806e6f6e6963}\\3400000000056B\\661"}, {"key": "\\\\REGISTRY\\A\\{c4363633-9e8a-11ea-ae26-167c9a143b2e}\\DefaultObjectStore\\ObjectTable\\666\\_FileId_"}, {"key": "\\\\REGISTRY\\A\\{c4363633-9e8a-11ea-ae26-167c9a143b2e}\\DefaultObjectStore\\ObjectTable\\666\\_ObjectLru_"}, {"key": "\\\\REGISTRY\\A\\{c4363633-9e8a-11ea-ae26-167c9a143b2e}\\DefaultObjectStore\\ObjectTable\\666\\_Usn_"}, {"key": "\\\\REGISTRY\\A\\{c4363633-9e8a-11ea-ae26-167c9a143b2e}\\DefaultObjectStore\\ObjectTable\\666\\_ObjectId_"}, {"key": "\\\\REGISTRY\\A\\{c4363633-9e8a-11ea-ae26-167c9a143b2e}\\DefaultObjectStore\\ObjectTable\\666\\AeFileID"}, {"key": "\\\\REGISTRY\\A\\{c4363633-9e8a-11ea-ae26-167c9a143b2e}\\DefaultObjectStore\\ObjectTable\\666\\_UsnJournalId_"}, {"key": "\\\\REGISTRY\\A\\{c4363633-9e8a-11ea-ae26-167c9a143b2e}\\DefaultObjectStore\\ObjectTable\\666\\AeProgramID"}, {"key": "HKU\\S-1-5-18\\Software\\Microsoft\\Windows\\CurrentVersion\\Internet Settings\\Wpad\\00-22-44-66-88-fe\\WpadDecisionTime", "value": "40 66 A9 21 98 32 D6 01"}, {"key": "HKU\\S-1-5-18\\Software\\Microsoft\\Windows\\CurrentVersion\\Internet Settings\\Wpad\\00-22-44-66-88-fe\\WpadDecision", "value": "0"}, {"key": "HKU\\S-1-5-18\\Software\\Microsoft\\Windows\\CurrentVersion\\Internet Settings\\Wpad\\00-22-44-66-88-fe\\WpadDecisionReason", "value": "2"}, {"key": "HKU\\S-1-5-21-575823232-3065301323-1442773979-1000\\Software\\Microsoft\\Windows\\CurrentVersion\\Internet Settings\\5.0\\Cache\\Cookies\\CachePrefix", "value": "Cookie:"}, {"key": "\\\\REGISTRY\\A\\{c4363633-9e8a-11ea-ae26-167c9a143b2e}\\DefaultObjectStore\\IndexTable\\FileIdIndex-{853201e6-2d75-11ea-a138-806e6f6e6963}\\1000000009069\\663"}, {"key": "\\\\REGISTRY\\A\\{c4363633-9e8a-11ea-ae26-167c9a143b2e}\\DefaultObjectStore\\ObjectTable\\665\\Indexes\\FileIdIndex-{853201e6-2d75-11ea-a138-806e6f6e6963}\\6000000009A6F"}, {"key": "HKU\\S-1-5-21-575823232-3065301323-1442773979-1000_CLASSES\\Local Settings\\MuiCache\\17b\\52C64B7E\\LanguageList", "value": "en-US\nen\n"}, {"key": "\\\\REGISTRY\\A\\{c4363633-9e8a-11ea-ae26-167c9a143b2e}\\DefaultObjectStore\\IndexTable\\FileIdIndex-{853201e6-2d75-11ea-a138-806e6f6e6963}\\_IndexName_"}, {"key": "HKLM\\SOFTWARE\\Microsoft\\Windows NT\\CurrentVersion\\Perflib\\Last Counter", "value": "12642"}, {"key": "HKLM\\SOFTWARE\\Microsoft\\Windows NT\\CurrentVersion\\Perflib\\Last Help", "value": "12643"}, {"key": "HKLM\\SOFTWARE\\Microsoft\\Windows NT\\CurrentVersion\\Perflib\\Updating"}, {"key": "HKLM\\SYSTEM\\ControlSet001\\Control\\DeviceClasses\\{ad498944-762f-11d0-8dcb-00c04fc3358c}\\##?#SW#{eeab7790-c514-11d1-b42b-00805fc1270e}#asyncmac#{ad498944-762f-11d0-8dcb-00c04fc3358c}\\DeviceInstance", "value": "SW\\{eeab7790-c514-11d1-b42b-00805fc1270e}\\asyncmac"}, {"key": "\\\\REGISTRY\\A\\{c4363633-9e8a-11ea-ae26-167c9a143b2e}\\DefaultObjectStore\\ObjectTable\\667\\_FileId_"}, {"key": "\\\\REGISTRY\\A\\{c4363633-9e8a-11ea-ae26-167c9a143b2e}\\DefaultObjectStore\\ObjectTable\\667\\_ObjectLru_"}, {"key": "\\\\REGISTRY\\A\\{c4363633-9e8a-11ea-ae26-167c9a143b2e}\\DefaultObjectStore\\ObjectTable\\667\\_Usn_"}, {"key": "\\\\REGISTRY\\A\\{c4363633-9e8a-11ea-ae26-167c9a143b2e}\\DefaultObjectStore\\ObjectTable\\667\\_ObjectId_"}, {"key": "\\\\REGISTRY\\A\\{c4363633-9e8a-11ea-ae26-167c9a143b2e}\\DefaultObjectStore\\ObjectTable\\667\\AeFileID"}, {"key": "\\\\REGISTRY\\A\\{c4363633-9e8a-11ea-ae26-167c9a143b2e}\\DefaultObjectStore\\ObjectTable\\667\\_UsnJournalId_"}, {"key": "\\\\REGISTRY\\A\\{c4363633-9e8a-11ea-ae26-167c9a143b2e}\\DefaultObjectStore\\ObjectTable\\667\\AeProgramID"}, {"key": "\\\\REGISTRY\\A\\{c4363633-9e8a-11ea-ae26-167c9a143b2e}\\DefaultObjectStore\\LruList\\0000000000002B67\\ObjectLru"}, {"key": "\\\\REGISTRY\\A\\{c4363633-9e8a-11ea-ae26-167c9a143b2e}\\DefaultObjectStore\\LruList\\0000000000002B67\\ObjectId"}, {"key": "HKLM\\SYSTEM\\ControlSet001\\Control\\DeviceClasses\\{cac88484-7515-4c03-82e6-71a87abac361}\\##?#SW#{eeab7790-c514-11d1-b42b-00805fc1270e}#asyncmac#{cac88484-7515-4c03-82e6-71a87abac361}\\Control\\ReferenceCount", "value": "1"}, {"key": "HKU\\S-1-5-18\\Software\\Microsoft\\Windows\\CurrentVersion\\Internet Settings\\ProxyEnable", "value": "0"}, {"key": "HKLM\\SYSTEM\\ControlSet001\\Control\\Nsi\\{eb004a03-9b1a-11d4-9123-0050047759bc}\\22\\(Default)"}, {"key": "\\\\REGISTRY\\A\\{c4363633-9e8a-11ea-ae26-167c9a143b2e}\\DefaultObjectStore\\LruList\\0000000000002B79\\ObjectLru"}, {"key": "\\\\REGISTRY\\A\\{c4363633-9e8a-11ea-ae26-167c9a143b2e}\\DefaultObjectStore\\LruList\\0000000000002B79\\ObjectId"}, {"key": "HKLM\\SYSTEM\\ControlSet001\\Control\\Nsi\\{eb004a03-9b1a-11d4-9123-0050047759bc}\\24\\ffffffffffffffffffffffffffffff00", "value": "00 00 00 00 00 00 00 00 00 00 00 00 FF FF FF FF FF FF FF FF FF FF FF FF"}, {"key": "HKLM\\SYSTEM\\ControlSet001\\Control\\Nsi\\{eb004a03-9b1a-11d4-9123-0050047759bc}\\24\\ffffffffffffffffffffffffffffff01", "value": "00 00 00 00 6E 00 00 00 20 00 00 00 FF FF FF FF FF FF FF FF FF FF FF FF"}, {"key": "HKLM\\SYSTEM\\ControlSet001\\Control\\Nsi\\{eb004a03-9b1a-11d4-9123-0050047759bc}\\24\\ffffffffffffffffffffffffffffff02", "value": "01 00 00 00 5A 00 00 00 D6 17 00 00 FF FF FF FF FF FF FF FF FF FF FF FF"}, {"key": "HKLM\\SYSTEM\\ControlSet001\\Control\\Nsi\\{eb004a03-9b1a-11d4-9123-0050047759bc}\\24\\ffffffffffffffffffffffffffffff03", "value": "00 00 00 00 00 00 00 00 00 00 00 00 FF FF FF FF FF FF FF FF FF FF FF FF"}, {"key": "HKU\\S-1-5-21-575823232-3065301323-1442773979-1000\\Software\\Microsoft\\Windows\\CurrentVersion\\Internet Settings\\5.0\\Cache\\History\\CachePrefix", "value": "Visited:"}, {"key": "\\\\REGISTRY\\A\\{c4363633-9e8a-11ea-ae26-167c9a143b2e}\\DefaultObjectStore\\ObjectTable\\661\\Indexes\\FileIdIndex-{853201e6-2d75-11ea-a138-806e6f6e6963}\\3400000000056B"}, {"key": "Software\\Microsoft\\Windows\\CurrentVersion\\Internet Settings\\ProxyEnable", "value": "0"}, {"key": "Software\\Microsoft\\Windows\\CurrentVersion\\Internet Settings\\Connections\\SavedLegacySettings", "value": "F"}, {"key": "HKCU\\Software\\Microsoft\\Windows\\CurrentVersion\\Internet Settings\\5.0\\Cache\\Content\\CachePrefix"}, {"key": "HKCU\\Software\\Microsoft\\Windows\\CurrentVersion\\Internet Settings\\5.0\\Cache\\Cookies\\CachePrefix", "value": "Cookie:"}, {"key": "HKCU\\Software\\Microsoft\\Windows\\CurrentVersion\\Internet Settings\\5.0\\Cache\\History\\CachePrefix", "value": "Visited:"}, {"key": "HKLM\\System\\CurrentControlSet\\services\\mssecsvc2.0\\Start", "value": "DWORD (0x00000002)"}, {"key": "HKLM\\System\\CurrentControlSet\\services\\mssecsvc2.0\\ImagePath", "value": "C:\\Users\\<USER>\\Downloads\\lhdfrgui.exe -m security"}, {"key": "HKLM\\System\\CurrentControlSet\\services\\hzabcojofyn317\\Start", "value": "DWORD (0x00000002)"}, {"key": "HKLM\\System\\CurrentControlSet\\services\\hzabcojofyn317\\ImagePath", "value": "cmd.exe /c \"C:\\ProgramData\\hzabcojofyn317\\tasksche.exe\""}], "tags": ["DIRECT_CPU_CLOCK_ACCESS", "CHECKS_NETWORK_ADAPTERS", "RUNTIME_MODULES"], "registry_keys_deleted": ["HKLM\\SYSTEM\\ControlSet001\\Services\\Tcpip\\Parameters\\DhcpNameServer", "HKLM\\SYSTEM\\ControlSet001\\Services\\Tcpip\\Parameters\\DhcpDomain", "HKLM\\SYSTEM\\ControlSet001\\Services\\WmiApRpl\\Performance\\First Counter", "HKLM\\SYSTEM\\ControlSet001\\Services\\WmiApRpl\\Performance\\Last Counter", "HKLM\\SYSTEM\\ControlSet001\\Services\\WmiApRpl\\Performance\\First Help", "HKLM\\SYSTEM\\ControlSet001\\Services\\WmiApRpl\\Performance\\Last Help", "HKLM\\SYSTEM\\ControlSet001\\Services\\WmiApRpl\\Performance\\Object List", "HKLM\\SYSTEM\\ControlSet001\\Services\\Tcpip\\Parameters\\Interfaces\\{b5da8633-954c-4495-ae46-0bb5b5fb1cdc}\\DhcpNameServer", "HKLM\\SYSTEM\\ControlSet001\\Services\\Tcpip\\Parameters\\Interfaces\\{b5da8633-954c-4495-ae46-0bb5b5fb1cdc}\\DhcpDomain", "HKLM\\SYSTEM\\ControlSet001\\Services\\Tcpip\\Parameters\\Interfaces\\{b5da8633-954c-4495-ae46-0bb5b5fb1cdc}\\DhcpSubnetMaskOpt", "HKLM\\SYSTEM\\ControlSet001\\Services\\Tcpip\\Parameters\\Interfaces\\{b5da8633-954c-4495-ae46-0bb5b5fb1cdc}\\DhcpDefaultGateway"], "services_created": ["mssecsvc2.0"], "text_highlighted": ["C:\\Windows\\system32\\cmd.exe"], "ids_alerts": [{"rule_category": "A Network Trojan was detected", "alert_severity": "high", "rule_msg": "ET MALWARE Possible WannaCry DNS Lookup 2", "tags": ["cve-2017-0144"], "rule_raw": "alert dns $HOME_NET any -> any any (msg:\"ET MALWARE Possible WannaCry DNS Lookup 2\"; dns.query; content:\"ifferfsodp9ifjaposdfjhgosurijfaewrwergwea\"; nocase; fast_pattern; reference:cve,2017-0144; reference:url,www.endgame.com/blog/wcrywanacry-ransomware-technical-analysis; reference:url,www.bleepingcomputer.com/news/security/telefonica-tells-employees-to-shut-down-computers-amid-massive-ransomware-outbreak/; classtype:trojan-activity; sid:2024293; rev:6; metadata:affected_product Windows_XP_Vista_7_8_10_Server_32_64_Bit, attack_target Client_Endpoint, created_at 2017_05_14, deployment Perimeter, former_category TROJAN, malware_family wannacry, performance_impact Moderate, signature_severity Critical, tag Ransomware, updated_at 2020_09_01;)", "rule_references": ["https://cve.mitre.org/cgi-bin/cvename.cgi?name=2017-0144", "https://www.endgame.com/blog/wcrywanacry-ransomware-technical-analysis", "https://www.bleepingcomputer.com/news/security/telefonica-tells-employees-to-shut-down-computers-amid-massive-ransomware-outbreak/"], "rule_source": "Proofpoint Emerging Threats Open", "rule_url": "https://rules.emergingthreats.net/", "rule_id": "1:2024293"}, {"rule_category": "Misc activity", "alert_severity": "low", "rule_msg": "ET SCAN Behavioral Unusual Port 445 traffic Potential Scan or Infection", "rule_raw": "alert tcp $HOME_NET any -> any 445 (msg:\"ET SCAN Behavioral Unusual Port 445 traffic Potential Scan or Infection\"; flow:to_server; flags: S,12; threshold: type both, track by_src, count 70 , seconds 60; reference:url,doc.emergingthreats.net/2001569; classtype:misc-activity; sid:2001569; rev:15; metadata:created_at 2010_07_30, former_category SCAN, updated_at 2017_05_11;)", "alert_context": {"dest_port": 445, "dest_ip": "177.159.165.21"}, "rule_references": ["https://doc.emergingthreats.net/2001569"], "rule_source": "Proofpoint Emerging Threats Open", "rule_url": "https://rules.emergingthreats.net/", "rule_id": "1:2001569"}, {"rule_category": "attempted-recon", "alert_severity": "medium", "rule_msg": "(port_scan) TCP filtered portsweep", "rule_raw": "alert ( gid:122; sid:7; rev: 2; msg:\"(port_scan) TCP filtered portsweep\"; metadata: rule-type preproc; classtype:attempted-recon;)", "alert_context": {"dest_port": 445, "dest_ip": "141.3.91.125"}, "rule_url": "https://www.snort.org/downloads/#rule-downloads", "rule_source": "Snort registered user ruleset", "rule_id": "122:7"}, {"rule_category": "misc-activity", "alert_severity": "low", "rule_msg": "PROTOCOL-ICMP Destination Unreachable Network Unreachable", "rule_raw": "alert icmp $EXTERNAL_NET any -> $HOME_NET any ( msg:\"PROTOCOL-ICMP Destination Unreachable Network Unreachable\"; icode:0; itype:3; metadata:ruleset community; classtype:misc-activity; sid:401; rev:9; )", "alert_context": {"src_ip": "172.253.66.148"}, "rule_url": "https://www.snort.org/downloads/#rule-downloads", "rule_source": "Snort registered user ruleset", "rule_id": "1:401"}, {"rule_category": "attempted-recon", "alert_severity": "medium", "rule_msg": "(icmp4) ICMP destination unreachable communication administratively prohibited", "rule_raw": "alert ( gid:116; sid:441; rev: 2; msg:\"(icmp4) ICMP destination unreachable communication administratively prohibited\"; metadata: rule-type decode; classtype:attempted-recon;)", "alert_context": {"src_ip": "178.13.252.53"}, "rule_url": "https://www.snort.org/downloads/#rule-downloads", "rule_source": "Snort registered user ruleset", "rule_id": "116:441"}, {"rule_category": "misc-activity", "alert_severity": "low", "rule_msg": "DELETED ICMP Destination Unreachable Communication Administratively Prohibited", "rule_raw": "alert icmp any any -> any any ( msg:\"DELETED ICMP Destination Unreachable Communication Administratively Prohibited\"; icode:13; itype:3; classtype:misc-activity; sid:485; rev:7; )", "alert_context": {"src_ip": "178.13.252.53"}, "rule_url": "https://www.snort.org/downloads/#rule-downloads", "rule_source": "Snort registered user ruleset", "rule_id": "1:485"}, {"rule_category": "attempted-recon", "alert_severity": "medium", "rule_msg": "(icmp4) ICMP destination unreachable communication with destination network is administratively prohibited", "rule_raw": "alert ( gid:116; sid:443; rev: 2; msg:\"(icmp4) ICMP destination unreachable communication with destination network is administratively prohibited\"; metadata: rule-type decode; classtype:attempted-recon;)", "alert_context": {"src_ip": "194.226.158.32"}, "rule_url": "https://www.snort.org/downloads/#rule-downloads", "rule_source": "Snort registered user ruleset", "rule_id": "116:443"}, {"rule_category": "misc-activity", "alert_severity": "low", "rule_msg": "DELETED ICMP Destination Unreachable Communication with Destination Network is Administratively Prohibited", "rule_raw": "alert icmp any any -> any any ( msg:\"DELETED ICMP Destination Unreachable Communication with Destination Network is Administratively Prohibited\"; icode:9; itype:3; classtype:misc-activity; sid:487; rev:7; )", "alert_context": {"src_ip": "194.226.158.32"}, "rule_url": "https://www.snort.org/downloads/#rule-downloads", "rule_source": "Snort registered user ruleset", "rule_id": "1:487"}], "modules_loaded": ["Secur32.dll", "SHELL32.dll", "ADVAPI32.dll", "api-ms-win-downlevel-advapi32-l2-1-0.dll", "api-ms-win-downlevel-ole32-l1-1-0.dll", "WS2_32.dll", "winhttp.dll", "IPHLPAPI.DLL", "api-ms-win-downlevel-shlwapi-l2-1-0.dll", "DNSAPI.dll", "urlmon.dll", "OLEAUT32.dll", "ole32.dll", "dhcpcsvc.DLL", "API-MS-Win-Security-LSALookup-L1-1-0.dll", "CRYPTBASE.dll"], "registry_keys_opened": ["HKCU\\SOFTWARE\\Microsoft\\Windows\\CurrentVersion\\Internet Settings", "HKLM\\Software\\Microsoft\\Windows\\CurrentVersion\\Internet Settings\\5.0\\Cache", "HKLM\\Software\\Policies\\Microsoft\\Internet Explorer\\Main\\FeatureControl", "HKLM\\Software\\Microsoft\\Internet Explorer\\Main\\FeatureControl", "HKCU\\Software\\Microsoft\\Internet Explorer\\Main\\FeatureControl\\FEATURE_HTTP_USERNAME_PASSWORD_DISABLE", "HKCU\\Software\\Microsoft\\Internet Explorer\\Main\\FeatureControl\\FEATURE_CLIENTAUTHCERTFILTER", "HKCU\\Software\\Microsoft\\Internet Explorer\\Main\\FeatureControl\\RETRY_HEADERONLYPOST_ONCONNECTIONRESET", "HKCU\\Software\\Microsoft\\Internet Explorer\\Main\\FeatureControl\\FEATURE_MIME_HANDLING", "HKCU\\Software\\Microsoft\\Internet Explorer\\Main\\FeatureControl\\FEATURE_BYPASS_CACHE_FOR_CREDPOLICY_KB936611", "HKCU\\Software\\Microsoft\\Internet Explorer\\Main\\FeatureControl\\FEATURE_IGNORE_MAPPINGS_FOR_CREDPOLICY", "HKCU\\Software\\Microsoft\\Internet Explorer\\Main\\FeatureControl\\FEATURE_INCLUDE_PORT_IN_SPN_KB908209", "HKCU\\Software\\Microsoft\\Internet Explorer\\Main\\FeatureControl\\FEATURE_BUFFERBREAKING_818408", "HKCU\\Software\\Microsoft\\Internet Explorer\\Main\\FeatureControl\\FEATURE_SKIP_POST_RETRY_ON_INTERNETWRITEFILE_KB895954", "HKCU\\Software\\Microsoft\\Internet Explorer\\Main\\FeatureControl\\FEATURE_FIX_CHUNKED_PROXY_SCRIPT_DOWNLOAD_KB843289", "HKCU\\Software\\Microsoft\\Internet Explorer\\Main\\FeatureControl\\FEATURE_USE_CNAME_FOR_SPN_KB911149", "HKCU\\Software\\Microsoft\\Internet Explorer\\Main\\FeatureControl\\FEATURE_PERMIT_CACHE_FOR_AUTHENTICATED_FTP_KB910274", "HKCU\\Software\\Microsoft\\Internet Explorer\\Main\\FeatureControl\\FEATURE_DISABLE_UNICODE_HANDLE_CLOSING_CALLBACK", "HKCU\\Software\\Microsoft\\Internet Explorer\\Main\\FeatureControl\\FEATURE_DISALLOW_NULL_IN_RESPONSE_HEADERS", "HKCU\\Software\\Microsoft\\Internet Explorer\\Main\\FeatureControl\\FEATURE_DIGEST_NO_EXTRAS_IN_URI", "HKLM\\Software\\Microsoft\\Internet Explorer\\Main\\FeatureControl\\FEATURE_ENABLE_PASSPORT_SESSION_STORE_KB948608", "HKCU\\Software\\Microsoft\\Internet Explorer\\Main\\FeatureControl\\FEATURE_EXCLUDE_INVALID_CLIENT_CERT_KB929477", "HKCU\\Software\\Microsoft\\Internet Explorer\\Main\\FeatureControl\\FEATURE_USE_UTF8_FOR_BASIC_AUTH_KB967545", "HKCU\\Software\\Microsoft\\Internet Explorer\\Main\\FeatureControl\\FEATURE_RETURN_FAILED_CONNECT_CONTENT_KB942615", "HKCU\\Software\\Microsoft\\Internet Explorer\\Main\\FeatureControl\\FEATURE_PRESERVE_SPACES_IN_FILENAMES_KB952730", "HKCU\\Software\\Microsoft\\Internet Explorer\\Main\\FeatureControl\\FEATURE_ENABLE_PROXY_CACHE_REFRESH_KB2983228", "HKLM\\Software\\Policies\\Microsoft\\Windows\\CurrentVersion\\Internet Settings", "HKLM\\Software\\Policies\\Microsoft\\Windows\\CurrentVersion\\Internet Settings\\SecureProtocols", "HKCU\\Software\\Microsoft\\Windows\\CurrentVersion\\Internet Settings", "HKCU\\Software\\Microsoft\\Windows\\CurrentVersion\\Internet Settings\\SecureProtocols", "HKLM\\Software\\Policies", "HKCU\\Software", "HKLM\\Software\\Policies\\Microsoft\\Internet Explorer", "HKLM\\Software\\Policies\\Microsoft\\Windows\\CurrentVersion\\Internet Settings\\EnableHttp1_1", "HKCU\\Software\\Microsoft\\Windows\\CurrentVersion\\Internet Settings\\EnableHttp1_1", "HKLM\\Software\\Policies\\Microsoft\\Windows\\CurrentVersion\\Internet Settings\\ProxyHttp1.1", "HKCU\\Software\\Microsoft\\Windows\\CurrentVersion\\Internet Settings\\ProxyHttp1.1", "HKCU\\SOFTWARE\\Microsoft\\Windows\\CurrentVersion\\Internet Settings\\5.0\\Cache", "HKLM\\SOFTWARE\\Policies\\Microsoft\\Windows\\CurrentVersion\\Internet Settings\\5.0\\Cache", "HKCU\\Software\\Microsoft\\Internet Explorer\\Main\\FeatureControl\\FEATURE_DISABLE_NOTIFY_UNVERIFIED_SPN_KB2385266", "HKCU\\Software\\Microsoft\\Internet Explorer\\Main\\FeatureControl\\FEATURE_COMPAT_USE_CONNECTION_BASED_NEGOTIATE_AUTH_KB2151543", "HKCU\\Software\\Microsoft\\Internet Explorer\\Main\\FeatureControl\\FEATURE_SCH_SEND_AUX_RECORD_KB_2618444", "HKCU\\Software\\Microsoft\\Internet Explorer\\Main", "HKCU\\Software\\Microsoft\\Internet Explorer\\Main\\FrameTabWindow", "HKCU\\Software\\Microsoft\\Internet Explorer\\Main\\FrameMerging", "HKCU\\Software\\Microsoft\\Internet Explorer\\Main\\SessionMerging", "HKCU\\Software\\Microsoft\\Internet Explorer\\Main\\AdminTabProcs", "HKLM\\Software\\Policies\\Microsoft\\Internet Explorer\\Main", "HKCU\\Software\\Microsoft\\Internet Explorer\\Main\\TabProcGrowth", "HKCU\\Software\\Microsoft\\Windows\\CurrentVersion\\Internet Settings\\Wpad", "HKCU\\Software\\Microsoft\\Windows\\CurrentVersion\\Internet Settings\\Wpad\\WpadOverride", "HKLM\\Software\\Policies\\Microsoft\\PeerDist\\Service", "HKLM\\Software\\Microsoft\\Windows NT\\CurrentVersion\\PeerDist\\Service", "HKLM\\System\\Setup", "HKCU\\Software\\Microsoft\\Windows\\CurrentVersion\\Internet Settings\\ProxyEnable", "HKCU\\Software\\Microsoft\\Windows\\CurrentVersion\\Internet Settings\\ProxyServer", "HKCU\\Software\\Microsoft\\Windows\\CurrentVersion\\Internet Settings\\ProxyOverride", "HKCU\\Software\\Microsoft\\Windows\\CurrentVersion\\Internet Settings\\AutoConfigURL", "HKCU\\Software\\Microsoft\\Windows\\CurrentVersion\\Internet Settings\\AutoDetect", "HKCU\\Software\\Microsoft\\Windows\\CurrentVersion\\Internet Settings\\Connections", "Software\\Microsoft\\Windows\\CurrentVersion\\Internet Settings\\Connections\\SavedLegacySettings", "Software\\Microsoft\\Windows\\CurrentVersion\\Internet Settings\\Connections\\DefaultConnectionSettings", "HKCU\\Software\\Microsoft\\Internet Explorer\\Main\\FeatureControl\\FEATURE_IGNORE_POLICIES_ZONEMAP_IF_ESC_ENABLED_KB918915", "HKCU\\Software\\Microsoft\\Internet Explorer\\Main\\FeatureControl\\FEATURE_ZONES_CHECK_ZONEMAP_POLICY_KB941001", "HKLM\\Software\\Policies\\Microsoft\\Windows\\CurrentVersion\\Internet Settings\\ZoneMap", "HKCU\\Software\\Microsoft\\Internet Explorer\\Security", "HKCU\\Software\\Microsoft\\Internet Explorer\\Security\\DisableSecuritySettingsCheck", "HKLM\\System\\Setup\\SystemSetupInProgress", "HKCU\\Software\\Microsoft\\Windows\\CurrentVersion\\Internet Settings\\Zones", "HKCU\\Software\\Microsoft\\Windows\\CurrentVersion\\Internet Settings\\Zones\\0", "HKCU\\Software\\Microsoft\\Windows\\CurrentVersion\\Internet Settings\\Zones\\1", "HKCU\\Software\\Microsoft\\Windows\\CurrentVersion\\Internet Settings\\Zones\\2", "HKCU\\Software\\Microsoft\\Windows\\CurrentVersion\\Internet Settings\\Zones\\3", "HKCU\\Software\\Microsoft\\Windows\\CurrentVersion\\Internet Settings\\Zones\\4", "HKCU\\Software\\Microsoft\\Internet Explorer\\Main\\FeatureControl\\FEATURE_LOCALMACHINE_LOCKDOWN", "HKLM\\Software\\Policies\\Microsoft\\Windows\\CurrentVersion\\Internet Settings\\CreateUriCacheSize", "HKCU\\Software\\Microsoft\\Windows\\CurrentVersion\\Internet Settings\\CreateUriCacheSize", "HKLM\\Software\\Policies\\Microsoft\\Windows\\CurrentVersion\\Internet Settings\\EnablePunycode", "HKCU\\Software\\Microsoft\\Windows\\CurrentVersion\\Internet Settings\\EnablePunycode", "HKCU\\Software\\Microsoft\\Internet Explorer\\Main\\FeatureControl\\FEATURE_ALLOW_REVERSE_SOLIDUS_IN_USERINFO_KB932562", "HKCU\\Software\\Microsoft\\Windows\\CurrentVersion\\Internet Settings\\5.0\\Cache\\Content", "HKCU\\Software\\Microsoft\\Windows\\CurrentVersion\\Internet Settings\\5.0\\Cache\\Cookies", "HKCU\\Software\\Microsoft\\Windows\\CurrentVersion\\Internet Settings\\5.0\\Cache\\History", "HKLM\\Software\\Microsoft\\OleAut", "Software\\Microsoft\\Windows\\CurrentVersion\\Internet Settings\\Wpad\\{728E2140-7495-4311-B833-F089070414CB}"], "ip_traffic": [{"transport_layer_protocol": "UDP", "destination_ip": "<MACHINE_DNS_SERVER>", "destination_port": 53}, {"transport_layer_protocol": "TCP", "destination_ip": "205.11.129.238", "destination_port": 445}, {"transport_layer_protocol": "TCP", "destination_ip": "138.101.63.81", "destination_port": 445}, {"transport_layer_protocol": "TCP", "destination_ip": "150.165.7.163", "destination_port": 445}, {"transport_layer_protocol": "TCP", "destination_ip": "106.156.163.163", "destination_port": 445}, {"transport_layer_protocol": "TCP", "destination_ip": "109.138.25.199", "destination_port": 445}, {"transport_layer_protocol": "TCP", "destination_ip": "185.223.165.69", "destination_port": 445}, {"transport_layer_protocol": "TCP", "destination_ip": "59.93.57.21", "destination_port": 445}, {"transport_layer_protocol": "TCP", "destination_ip": "101.88.169.212", "destination_port": 445}, {"transport_layer_protocol": "TCP", "destination_ip": "134.204.109.125", "destination_port": 445}, {"transport_layer_protocol": "TCP", "destination_ip": "32.106.59.17", "destination_port": 445}, {"transport_layer_protocol": "TCP", "destination_ip": "197.99.178.117", "destination_port": 445}, {"transport_layer_protocol": "TCP", "destination_ip": "102.219.48.214", "destination_port": 445}, {"transport_layer_protocol": "TCP", "destination_ip": "179.240.113.202", "destination_port": 445}, {"transport_layer_protocol": "TCP", "destination_ip": "100.199.244.205", "destination_port": 445}, {"transport_layer_protocol": "TCP", "destination_ip": "144.154.158.182", "destination_port": 445}, {"transport_layer_protocol": "TCP", "destination_ip": "207.33.62.23", "destination_port": 445}, {"transport_layer_protocol": "TCP", "destination_ip": "129.46.30.44", "destination_port": 445}, {"transport_layer_protocol": "TCP", "destination_ip": "117.118.219.94", "destination_port": 445}, {"transport_layer_protocol": "TCP", "destination_ip": "51.54.57.39", "destination_port": 445}, {"transport_layer_protocol": "TCP", "destination_ip": "91.181.245.161", "destination_port": 445}, {"transport_layer_protocol": "TCP", "destination_ip": "86.212.241.61", "destination_port": 445}, {"transport_layer_protocol": "TCP", "destination_ip": "70.228.171.67", "destination_port": 445}, {"transport_layer_protocol": "TCP", "destination_ip": "93.178.3.47", "destination_port": 445}, {"transport_layer_protocol": "TCP", "destination_ip": "47.19.101.174", "destination_port": 445}, {"transport_layer_protocol": "TCP", "destination_ip": "192.158.117.45", "destination_port": 445}, {"transport_layer_protocol": "TCP", "destination_ip": "164.222.30.60", "destination_port": 445}, {"transport_layer_protocol": "TCP", "destination_ip": "51.134.58.34", "destination_port": 445}, {"transport_layer_protocol": "TCP", "destination_ip": "124.241.131.70", "destination_port": 445}, {"transport_layer_protocol": "TCP", "destination_ip": "160.179.226.196", "destination_port": 445}, {"transport_layer_protocol": "TCP", "destination_ip": "141.3.91.125", "destination_port": 445}, {"transport_layer_protocol": "TCP", "destination_ip": "29.98.83.164", "destination_port": 445}, {"transport_layer_protocol": "TCP", "destination_ip": "116.127.55.87", "destination_port": 445}, {"transport_layer_protocol": "TCP", "destination_ip": "35.182.164.235", "destination_port": 445}, {"transport_layer_protocol": "TCP", "destination_ip": "134.161.151.125", "destination_port": 445}, {"transport_layer_protocol": "TCP", "destination_ip": "13.87.84.200", "destination_port": 445}, {"transport_layer_protocol": "TCP", "destination_ip": "58.120.130.161", "destination_port": 445}, {"transport_layer_protocol": "TCP", "destination_ip": "212.70.114.147", "destination_port": 445}, {"transport_layer_protocol": "TCP", "destination_ip": "26.176.56.245", "destination_port": 445}, {"transport_layer_protocol": "TCP", "destination_ip": "82.200.105.215", "destination_port": 445}, {"transport_layer_protocol": "TCP", "destination_ip": "41.188.61.80", "destination_port": 445}, {"transport_layer_protocol": "TCP", "destination_ip": "129.168.148.48", "destination_port": 445}, {"transport_layer_protocol": "TCP", "destination_ip": "124.120.175.137", "destination_port": 445}, {"transport_layer_protocol": "TCP", "destination_ip": "193.20.212.223", "destination_port": 445}, {"transport_layer_protocol": "TCP", "destination_ip": "128.204.215.70", "destination_port": 445}, {"transport_layer_protocol": "TCP", "destination_ip": "162.245.50.189", "destination_port": 445}, {"transport_layer_protocol": "TCP", "destination_ip": "72.11.113.62", "destination_port": 445}, {"transport_layer_protocol": "TCP", "destination_ip": "12.76.135.93", "destination_port": 445}, {"transport_layer_protocol": "TCP", "destination_ip": "200.162.133.225", "destination_port": 445}, {"transport_layer_protocol": "TCP", "destination_ip": "34.129.8.51", "destination_port": 445}, {"transport_layer_protocol": "TCP", "destination_ip": "88.55.23.64", "destination_port": 445}, {"transport_layer_protocol": "TCP", "destination_ip": "181.251.130.124", "destination_port": 445}, {"transport_layer_protocol": "TCP", "destination_ip": "8.254.6.210", "destination_port": 445}, {"transport_layer_protocol": "TCP", "destination_ip": "2.167.145.129", "destination_port": 445}, {"transport_layer_protocol": "TCP", "destination_ip": "57.224.171.117", "destination_port": 445}, {"transport_layer_protocol": "TCP", "destination_ip": "119.250.118.76", "destination_port": 445}, {"transport_layer_protocol": "TCP", "destination_ip": "207.231.190.129", "destination_port": 445}, {"transport_layer_protocol": "TCP", "destination_ip": "22.177.205.24", "destination_port": 445}, {"transport_layer_protocol": "TCP", "destination_ip": "77.77.12.40", "destination_port": 445}, {"transport_layer_protocol": "TCP", "destination_ip": "203.135.19.126", "destination_port": 445}, {"transport_layer_protocol": "TCP", "destination_ip": "185.203.168.37", "destination_port": 445}, {"transport_layer_protocol": "TCP", "destination_ip": "166.238.229.197", "destination_port": 445}, {"transport_layer_protocol": "TCP", "destination_ip": "194.183.137.29", "destination_port": 445}, {"transport_layer_protocol": "TCP", "destination_ip": "124.125.212.11", "destination_port": 445}, {"transport_layer_protocol": "TCP", "destination_ip": "111.25.17.126", "destination_port": 445}, {"transport_layer_protocol": "TCP", "destination_ip": "128.227.33.90", "destination_port": 445}, {"transport_layer_protocol": "TCP", "destination_ip": "184.166.7.41", "destination_port": 445}, {"transport_layer_protocol": "TCP", "destination_ip": "154.157.60.99", "destination_port": 445}, {"transport_layer_protocol": "TCP", "destination_ip": "32.31.173.251", "destination_port": 445}, {"transport_layer_protocol": "TCP", "destination_ip": "50.92.222.137", "destination_port": 445}, {"transport_layer_protocol": "TCP", "destination_ip": "76.11.77.141", "destination_port": 445}, {"transport_layer_protocol": "TCP", "destination_ip": "187.230.80.81", "destination_port": 445}, {"transport_layer_protocol": "TCP", "destination_ip": "210.30.157.36", "destination_port": 445}, {"transport_layer_protocol": "TCP", "destination_ip": "159.144.43.69", "destination_port": 445}, {"transport_layer_protocol": "TCP", "destination_ip": "11.132.230.241", "destination_port": 445}, {"transport_layer_protocol": "TCP", "destination_ip": "103.212.201.253", "destination_port": 445}, {"transport_layer_protocol": "TCP", "destination_ip": "73.55.124.232", "destination_port": 445}, {"transport_layer_protocol": "TCP", "destination_ip": "79.72.10.207", "destination_port": 445}, {"transport_layer_protocol": "TCP", "destination_ip": "100.45.254.123", "destination_port": 445}, {"transport_layer_protocol": "TCP", "destination_ip": "20.147.137.134", "destination_port": 445}, {"transport_layer_protocol": "TCP", "destination_ip": "51.118.231.162", "destination_port": 445}, {"transport_layer_protocol": "TCP", "destination_ip": "126.167.130.226", "destination_port": 445}, {"transport_layer_protocol": "TCP", "destination_ip": "99.44.178.18", "destination_port": 445}, {"transport_layer_protocol": "TCP", "destination_ip": "136.52.14.105", "destination_port": 445}, {"transport_layer_protocol": "TCP", "destination_ip": "22.120.3.123", "destination_port": 445}, {"transport_layer_protocol": "TCP", "destination_ip": "80.0.160.218", "destination_port": 445}, {"transport_layer_protocol": "TCP", "destination_ip": "49.201.207.65", "destination_port": 445}, {"transport_layer_protocol": "TCP", "destination_ip": "78.26.147.104", "destination_port": 445}, {"transport_layer_protocol": "TCP", "destination_ip": "22.189.102.126", "destination_port": 445}, {"transport_layer_protocol": "TCP", "destination_ip": "221.64.76.199", "destination_port": 445}, {"transport_layer_protocol": "TCP", "destination_ip": "75.82.195.187", "destination_port": 445}, {"transport_layer_protocol": "TCP", "destination_ip": "66.153.224.214", "destination_port": 445}, {"transport_layer_protocol": "TCP", "destination_ip": "28.254.10.56", "destination_port": 445}, {"transport_layer_protocol": "TCP", "destination_ip": "62.140.12.249", "destination_port": 445}, {"transport_layer_protocol": "TCP", "destination_ip": "113.83.123.26", "destination_port": 445}, {"transport_layer_protocol": "TCP", "destination_ip": "108.168.104.132", "destination_port": 445}, {"transport_layer_protocol": "TCP", "destination_ip": "75.206.253.144", "destination_port": 445}, {"transport_layer_protocol": "TCP", "destination_ip": "56.35.199.17", "destination_port": 445}, {"transport_layer_protocol": "TCP", "destination_ip": "149.84.160.42", "destination_port": 445}, {"transport_layer_protocol": "TCP", "destination_ip": "212.207.114.222", "destination_port": 445}, {"transport_layer_protocol": "TCP", "destination_ip": "171.173.216.72", "destination_port": 445}, {"transport_layer_protocol": "TCP", "destination_ip": "54.197.172.24", "destination_port": 445}, {"transport_layer_protocol": "TCP", "destination_ip": "72.54.135.174", "destination_port": 445}, {"transport_layer_protocol": "TCP", "destination_ip": "19.237.11.39", "destination_port": 445}, {"transport_layer_protocol": "TCP", "destination_ip": "48.190.116.183", "destination_port": 445}, {"transport_layer_protocol": "TCP", "destination_ip": "218.13.246.251", "destination_port": 445}, {"transport_layer_protocol": "TCP", "destination_ip": "161.192.31.18", "destination_port": 445}, {"transport_layer_protocol": "TCP", "destination_ip": "214.96.164.110", "destination_port": 445}, {"transport_layer_protocol": "TCP", "destination_ip": "158.104.142.95", "destination_port": 445}, {"transport_layer_protocol": "TCP", "destination_ip": "54.52.171.132", "destination_port": 445}, {"transport_layer_protocol": "TCP", "destination_ip": "171.39.200.127", "destination_port": 445}, {"transport_layer_protocol": "TCP", "destination_ip": "72.109.47.161", "destination_port": 445}, {"transport_layer_protocol": "TCP", "destination_ip": "205.243.186.140", "destination_port": 445}, {"transport_layer_protocol": "TCP", "destination_ip": "148.127.183.15", "destination_port": 445}, {"transport_layer_protocol": "TCP", "destination_ip": "135.102.60.165", "destination_port": 445}, {"transport_layer_protocol": "TCP", "destination_ip": "89.247.188.237", "destination_port": 445}, {"transport_layer_protocol": "TCP", "destination_ip": "32.110.107.25", "destination_port": 445}, {"transport_layer_protocol": "TCP", "destination_ip": "21.138.239.73", "destination_port": 445}, {"transport_layer_protocol": "TCP", "destination_ip": "178.13.252.53", "destination_port": 445}, {"transport_layer_protocol": "TCP", "destination_ip": "109.234.208.63", "destination_port": 445}, {"transport_layer_protocol": "TCP", "destination_ip": "37.168.201.2", "destination_port": 445}, {"transport_layer_protocol": "TCP", "destination_ip": "130.16.249.9", "destination_port": 445}, {"transport_layer_protocol": "TCP", "destination_ip": "47.63.132.97", "destination_port": 445}, {"transport_layer_protocol": "TCP", "destination_ip": "106.62.195.25", "destination_port": 445}, {"transport_layer_protocol": "TCP", "destination_ip": "42.112.88.127", "destination_port": 445}, {"transport_layer_protocol": "TCP", "destination_ip": "174.19.2.189", "destination_port": 445}, {"transport_layer_protocol": "TCP", "destination_ip": "120.250.18.82", "destination_port": 445}, {"transport_layer_protocol": "TCP", "destination_ip": "146.28.121.78", "destination_port": 445}, {"transport_layer_protocol": "TCP", "destination_ip": "89.93.106.65", "destination_port": 445}, {"transport_layer_protocol": "TCP", "destination_ip": "96.187.166.157", "destination_port": 445}, {"transport_layer_protocol": "TCP", "destination_ip": "81.254.232.89", "destination_port": 445}, {"transport_layer_protocol": "TCP", "destination_ip": "27.229.190.161", "destination_port": 445}, {"transport_layer_protocol": "TCP", "destination_ip": "16.250.77.52", "destination_port": 445}, {"transport_layer_protocol": "TCP", "destination_ip": "180.167.153.64", "destination_port": 445}, {"transport_layer_protocol": "TCP", "destination_ip": "217.134.136.128", "destination_port": 445}, {"transport_layer_protocol": "TCP", "destination_ip": "134.145.111.115", "destination_port": 445}, {"transport_layer_protocol": "TCP", "destination_ip": "130.210.200.8", "destination_port": 445}, {"transport_layer_protocol": "TCP", "destination_ip": "109.68.248.139", "destination_port": 445}, {"transport_layer_protocol": "TCP", "destination_ip": "53.210.50.101", "destination_port": 445}, {"transport_layer_protocol": "TCP", "destination_ip": "10.134.166.70", "destination_port": 445}, {"transport_layer_protocol": "TCP", "destination_ip": "220.238.129.152", "destination_port": 445}, {"transport_layer_protocol": "TCP", "destination_ip": "77.67.164.79", "destination_port": 445}, {"transport_layer_protocol": "TCP", "destination_ip": "126.226.55.224", "destination_port": 445}, {"transport_layer_protocol": "TCP", "destination_ip": "105.126.22.205", "destination_port": 445}, {"transport_layer_protocol": "TCP", "destination_ip": "52.53.211.240", "destination_port": 445}, {"transport_layer_protocol": "TCP", "destination_ip": "45.10.219.226", "destination_port": 445}, {"transport_layer_protocol": "TCP", "destination_ip": "199.31.86.119", "destination_port": 445}, {"transport_layer_protocol": "TCP", "destination_ip": "7.176.7.90", "destination_port": 445}, {"transport_layer_protocol": "TCP", "destination_ip": "6.10.132.63", "destination_port": 445}, {"transport_layer_protocol": "TCP", "destination_ip": "9.88.50.68", "destination_port": 445}, {"transport_layer_protocol": "TCP", "destination_ip": "181.198.31.104", "destination_port": 445}, {"transport_layer_protocol": "TCP", "destination_ip": "204.7.150.29", "destination_port": 445}, {"transport_layer_protocol": "TCP", "destination_ip": "75.60.216.132", "destination_port": 445}, {"transport_layer_protocol": "TCP", "destination_ip": "1.129.95.162", "destination_port": 445}, {"transport_layer_protocol": "TCP", "destination_ip": "94.142.1.231", "destination_port": 445}, {"transport_layer_protocol": "TCP", "destination_ip": "42.181.14.215", "destination_port": 445}, {"transport_layer_protocol": "TCP", "destination_ip": "57.36.23.69", "destination_port": 445}, {"transport_layer_protocol": "TCP", "destination_ip": "4.155.6.145", "destination_port": 445}, {"transport_layer_protocol": "TCP", "destination_ip": "39.241.151.15", "destination_port": 445}, {"transport_layer_protocol": "TCP", "destination_ip": "93.12.15.221", "destination_port": 445}, {"transport_layer_protocol": "TCP", "destination_ip": "163.178.113.207", "destination_port": 445}, {"transport_layer_protocol": "TCP", "destination_ip": "85.228.21.247", "destination_port": 445}, {"transport_layer_protocol": "TCP", "destination_ip": "9.43.190.173", "destination_port": 445}, {"transport_layer_protocol": "TCP", "destination_ip": "186.229.50.152", "destination_port": 445}, {"transport_layer_protocol": "TCP", "destination_ip": "105.197.201.25", "destination_port": 445}, {"transport_layer_protocol": "TCP", "destination_ip": "163.136.199.195", "destination_port": 445}, {"transport_layer_protocol": "TCP", "destination_ip": "27.107.76.24", "destination_port": 445}, {"transport_layer_protocol": "TCP", "destination_ip": "2.83.185.121", "destination_port": 445}, {"transport_layer_protocol": "TCP", "destination_ip": "191.252.145.25", "destination_port": 445}, {"transport_layer_protocol": "TCP", "destination_ip": "167.10.80.149", "destination_port": 445}, {"transport_layer_protocol": "TCP", "destination_ip": "211.173.250.18", "destination_port": 445}, {"transport_layer_protocol": "TCP", "destination_ip": "45.4.121.48", "destination_port": 445}, {"transport_layer_protocol": "TCP", "destination_ip": "26.58.33.130", "destination_port": 445}, {"transport_layer_protocol": "TCP", "destination_ip": "65.130.43.99", "destination_port": 445}, {"transport_layer_protocol": "TCP", "destination_ip": "93.172.217.59", "destination_port": 445}, {"transport_layer_protocol": "TCP", "destination_ip": "74.176.105.203", "destination_port": 445}, {"transport_layer_protocol": "TCP", "destination_ip": "125.243.32.53", "destination_port": 445}, {"transport_layer_protocol": "TCP", "destination_ip": "122.28.203.188", "destination_port": 445}, {"transport_layer_protocol": "TCP", "destination_ip": "72.165.92.97", "destination_port": 445}, {"transport_layer_protocol": "TCP", "destination_ip": "115.169.165.0", "destination_port": 445}, {"transport_layer_protocol": "TCP", "destination_ip": "218.111.152.230", "destination_port": 445}, {"transport_layer_protocol": "TCP", "destination_ip": "153.236.190.37", "destination_port": 445}, {"transport_layer_protocol": "TCP", "destination_ip": "129.66.252.246", "destination_port": 445}, {"transport_layer_protocol": "TCP", "destination_ip": "163.38.100.225", "destination_port": 445}, {"transport_layer_protocol": "TCP", "destination_ip": "95.239.238.203", "destination_port": 445}, {"transport_layer_protocol": "TCP", "destination_ip": "144.71.171.131", "destination_port": 445}, {"transport_layer_protocol": "TCP", "destination_ip": "131.119.45.27", "destination_port": 445}, {"transport_layer_protocol": "TCP", "destination_ip": "40.222.212.228", "destination_port": 445}, {"transport_layer_protocol": "TCP", "destination_ip": "124.85.179.209", "destination_port": 445}, {"transport_layer_protocol": "TCP", "destination_ip": "216.128.220.131", "destination_port": 445}, {"transport_layer_protocol": "TCP", "destination_ip": "75.3.214.209", "destination_port": 445}, {"transport_layer_protocol": "TCP", "destination_ip": "28.168.251.176", "destination_port": 445}, {"transport_layer_protocol": "TCP", "destination_ip": "91.192.159.37", "destination_port": 445}, {"transport_layer_protocol": "TCP", "destination_ip": "105.146.140.89", "destination_port": 445}, {"transport_layer_protocol": "TCP", "destination_ip": "65.216.52.18", "destination_port": 445}, {"transport_layer_protocol": "TCP", "destination_ip": "195.70.34.186", "destination_port": 445}, {"transport_layer_protocol": "TCP", "destination_ip": "182.88.3.140", "destination_port": 445}, {"transport_layer_protocol": "TCP", "destination_ip": "54.72.215.64", "destination_port": 445}, {"transport_layer_protocol": "TCP", "destination_ip": "161.38.217.194", "destination_port": 445}, {"transport_layer_protocol": "TCP", "destination_ip": "162.3.187.33", "destination_port": 445}, {"transport_layer_protocol": "TCP", "destination_ip": "181.139.28.134", "destination_port": 445}, {"transport_layer_protocol": "TCP", "destination_ip": "169.89.98.73", "destination_port": 445}, {"transport_layer_protocol": "TCP", "destination_ip": "29.209.229.194", "destination_port": 445}, {"transport_layer_protocol": "TCP", "destination_ip": "8.125.5.214", "destination_port": 445}, {"transport_layer_protocol": "TCP", "destination_ip": "51.137.206.90", "destination_port": 445}, {"transport_layer_protocol": "TCP", "destination_ip": "115.123.232.236", "destination_port": 445}, {"transport_layer_protocol": "TCP", "destination_ip": "141.200.77.193", "destination_port": 445}, {"transport_layer_protocol": "TCP", "destination_ip": "155.230.13.35", "destination_port": 445}, {"transport_layer_protocol": "TCP", "destination_ip": "122.98.218.137", "destination_port": 445}, {"transport_layer_protocol": "TCP", "destination_ip": "104.40.248.168", "destination_port": 445}, {"transport_layer_protocol": "TCP", "destination_ip": "174.32.237.76", "destination_port": 445}, {"transport_layer_protocol": "TCP", "destination_ip": "200.213.79.0", "destination_port": 445}, {"transport_layer_protocol": "TCP", "destination_ip": "30.92.24.196", "destination_port": 445}, {"transport_layer_protocol": "TCP", "destination_ip": "65.241.176.138", "destination_port": 445}, {"transport_layer_protocol": "TCP", "destination_ip": "53.67.248.162", "destination_port": 445}, {"transport_layer_protocol": "TCP", "destination_ip": "123.198.65.44", "destination_port": 445}, {"transport_layer_protocol": "TCP", "destination_ip": "14.50.29.104", "destination_port": 445}, {"transport_layer_protocol": "TCP", "destination_ip": "82.124.73.119", "destination_port": 445}, {"transport_layer_protocol": "TCP", "destination_ip": "28.195.114.151", "destination_port": 445}, {"transport_layer_protocol": "TCP", "destination_ip": "89.115.132.232", "destination_port": 445}, {"transport_layer_protocol": "TCP", "destination_ip": "6.200.71.203", "destination_port": 445}, {"transport_layer_protocol": "TCP", "destination_ip": "220.9.42.87", "destination_port": 445}, {"transport_layer_protocol": "TCP", "destination_ip": "57.29.8.147", "destination_port": 445}, {"transport_layer_protocol": "TCP", "destination_ip": "8.20.224.174", "destination_port": 445}, {"transport_layer_protocol": "TCP", "destination_ip": "20.10.70.35", "destination_port": 445}, {"transport_layer_protocol": "TCP", "destination_ip": "26.139.174.130", "destination_port": 445}, {"transport_layer_protocol": "TCP", "destination_ip": "151.171.7.3", "destination_port": 445}, {"transport_layer_protocol": "TCP", "destination_ip": "161.235.228.249", "destination_port": 445}, {"transport_layer_protocol": "TCP", "destination_ip": "26.153.64.222", "destination_port": 445}, {"transport_layer_protocol": "TCP", "destination_ip": "133.162.5.117", "destination_port": 445}, {"transport_layer_protocol": "TCP", "destination_ip": "79.7.100.131", "destination_port": 445}, {"transport_layer_protocol": "TCP", "destination_ip": "145.83.145.242", "destination_port": 445}, {"transport_layer_protocol": "TCP", "destination_ip": "208.135.171.84", "destination_port": 445}, {"transport_layer_protocol": "TCP", "destination_ip": "206.186.22.146", "destination_port": 445}, {"transport_layer_protocol": "TCP", "destination_ip": "215.173.203.218", "destination_port": 445}, {"transport_layer_protocol": "TCP", "destination_ip": "111.194.173.242", "destination_port": 445}, {"transport_layer_protocol": "TCP", "destination_ip": "192.27.72.141", "destination_port": 445}, {"transport_layer_protocol": "TCP", "destination_ip": "178.45.172.112", "destination_port": 445}, {"transport_layer_protocol": "TCP", "destination_ip": "91.86.168.104", "destination_port": 445}, {"transport_layer_protocol": "TCP", "destination_ip": "158.127.17.228", "destination_port": 445}, {"transport_layer_protocol": "TCP", "destination_ip": "148.89.45.126", "destination_port": 445}, {"transport_layer_protocol": "TCP", "destination_ip": "214.209.80.232", "destination_port": 445}, {"transport_layer_protocol": "TCP", "destination_ip": "198.182.21.170", "destination_port": 445}, {"transport_layer_protocol": "TCP", "destination_ip": "14.54.77.220", "destination_port": 445}, {"transport_layer_protocol": "TCP", "destination_ip": "119.195.244.174", "destination_port": 445}, {"transport_layer_protocol": "TCP", "destination_ip": "9.96.92.93", "destination_port": 445}, {"transport_layer_protocol": "TCP", "destination_ip": "69.48.40.204", "destination_port": 445}, {"transport_layer_protocol": "TCP", "destination_ip": "93.193.227.183", "destination_port": 445}, {"transport_layer_protocol": "TCP", "destination_ip": "105.132.208.231", "destination_port": 445}, {"transport_layer_protocol": "TCP", "destination_ip": "75.205.79.246", "destination_port": 445}, {"transport_layer_protocol": "TCP", "destination_ip": "185.99.39.229", "destination_port": 445}, {"transport_layer_protocol": "TCP", "destination_ip": "194.180.139.9", "destination_port": 445}, {"transport_layer_protocol": "TCP", "destination_ip": "219.46.64.214", "destination_port": 445}, {"transport_layer_protocol": "TCP", "destination_ip": "118.86.131.171", "destination_port": 445}, {"transport_layer_protocol": "TCP", "destination_ip": "125.122.103.127", "destination_port": 445}, {"transport_layer_protocol": "TCP", "destination_ip": "150.85.57.101", "destination_port": 445}, {"transport_layer_protocol": "TCP", "destination_ip": "107.250.192.153", "destination_port": 445}, {"transport_layer_protocol": "TCP", "destination_ip": "141.57.208.168", "destination_port": 445}, {"transport_layer_protocol": "TCP", "destination_ip": "5.106.16.128", "destination_port": 445}, {"transport_layer_protocol": "TCP", "destination_ip": "168.73.6.9", "destination_port": 445}, {"transport_layer_protocol": "TCP", "destination_ip": "196.22.153.35", "destination_port": 445}, {"transport_layer_protocol": "TCP", "destination_ip": "126.136.145.72", "destination_port": 445}, {"transport_layer_protocol": "TCP", "destination_ip": "40.19.233.93", "destination_port": 445}, {"transport_layer_protocol": "TCP", "destination_ip": "16.120.217.58", "destination_port": 445}, {"transport_layer_protocol": "TCP", "destination_ip": "24.50.157.34", "destination_port": 445}, {"transport_layer_protocol": "TCP", "destination_ip": "21.232.171.154", "destination_port": 445}, {"transport_layer_protocol": "TCP", "destination_ip": "162.213.251.27", "destination_port": 445}, {"transport_layer_protocol": "TCP", "destination_ip": "205.136.188.135", "destination_port": 445}, {"transport_layer_protocol": "TCP", "destination_ip": "42.51.92.0", "destination_port": 445}, {"transport_layer_protocol": "TCP", "destination_ip": "138.35.198.66", "destination_port": 445}, {"transport_layer_protocol": "TCP", "destination_ip": "85.242.186.158", "destination_port": 445}, {"transport_layer_protocol": "TCP", "destination_ip": "75.170.9.131", "destination_port": 445}, {"transport_layer_protocol": "TCP", "destination_ip": "137.241.95.154", "destination_port": 445}, {"transport_layer_protocol": "TCP", "destination_ip": "223.113.246.143", "destination_port": 445}, {"transport_layer_protocol": "TCP", "destination_ip": "12.46.103.78", "destination_port": 445}, {"transport_layer_protocol": "TCP", "destination_ip": "5.252.241.51", "destination_port": 445}, {"transport_layer_protocol": "TCP", "destination_ip": "110.55.34.25", "destination_port": 445}, {"transport_layer_protocol": "TCP", "destination_ip": "137.44.239.4", "destination_port": 445}, {"transport_layer_protocol": "TCP", "destination_ip": "194.226.158.32", "destination_port": 445}, {"transport_layer_protocol": "TCP", "destination_ip": "97.87.9.82", "destination_port": 445}, {"transport_layer_protocol": "TCP", "destination_ip": "166.109.112.250", "destination_port": 445}, {"transport_layer_protocol": "TCP", "destination_ip": "163.126.42.142", "destination_port": 445}, {"transport_layer_protocol": "TCP", "destination_ip": "57.184.84.74", "destination_port": 445}, {"transport_layer_protocol": "TCP", "destination_ip": "204.146.162.6", "destination_port": 445}, {"transport_layer_protocol": "TCP", "destination_ip": "193.152.80.249", "destination_port": 445}, {"transport_layer_protocol": "TCP", "destination_ip": "7.11.237.138", "destination_port": 445}, {"transport_layer_protocol": "TCP", "destination_ip": "91.231.54.24", "destination_port": 445}, {"transport_layer_protocol": "TCP", "destination_ip": "174.198.26.130", "destination_port": 445}, {"transport_layer_protocol": "TCP", "destination_ip": "195.188.86.2", "destination_port": 445}, {"transport_layer_protocol": "TCP", "destination_ip": "30.130.55.37", "destination_port": 445}, {"transport_layer_protocol": "TCP", "destination_ip": "94.8.166.157", "destination_port": 445}, {"transport_layer_protocol": "TCP", "destination_ip": "69.36.214.130", "destination_port": 445}, {"transport_layer_protocol": "TCP", "destination_ip": "177.159.165.21", "destination_port": 445}, {"transport_layer_protocol": "TCP", "destination_ip": "205.49.162.68", "destination_port": 445}, {"transport_layer_protocol": "TCP", "destination_ip": "106.35.168.231", "destination_port": 445}, {"transport_layer_protocol": "TCP", "destination_ip": "170.195.112.207", "destination_port": 445}, {"transport_layer_protocol": "TCP", "destination_ip": "140.253.146.157", "destination_port": 445}, {"transport_layer_protocol": "TCP", "destination_ip": "108.80.177.231", "destination_port": 445}, {"transport_layer_protocol": "TCP", "destination_ip": "190.117.135.161", "destination_port": 445}, {"transport_layer_protocol": "TCP", "destination_ip": "185.174.103.150", "destination_port": 445}, {"transport_layer_protocol": "TCP", "destination_ip": "104.40.102.167", "destination_port": 445}], "processes_tree": [{"process_id": "2024", "name": "%CONHOST% \"-464306226-851367519719008150990521842-394017574-959799360411026720-660886838"}, {"process_id": "2320", "name": "%CONHOST% \"15164868772101513324-1996898007853399385880879792103470600-18055639251009404738"}, {"process_id": "1244", "name": "%CONHOST% \"-20834503-7634691791645538042-241691420545465520-2088001280-279374024-2102624805"}, {"process_id": "1284", "name": "cmd.exe /c \"%ProgramData%\\yuuaclhph815\\tasksche.exe\"", "children": [{"process_id": "2032", "name": "%ProgramData%\\yuuaclhph815\\tasksche.exe", "children": [{"process_id": "312", "name": "attrib +h +s Z:\\$RECYCLE"}, {"process_id": "852", "name": "taskdl.exe"}, {"process_id": "2188", "name": "icacls . /grant Everyone:F /T /C /Q"}, {"process_id": "2372", "name": "attrib +h +s D:\\$RECYCLE"}, {"process_id": "1112", "name": "attrib +h ."}]}]}, {"process_id": "508", "name": "%windir%\\system32\\DllHost.exe /Processid:{AB8902B4-09CA-4BB6-B78D-A8F59079A8D5}"}, {"process_id": "3024", "name": "wmiadap.exe /F /T /R"}, {"process_id": "3068", "name": "%windir%\\system32\\wbem\\wmiprvse.exe"}, {"process_id": "2692", "name": "%windir%\\system32\\DllHost.exe /Processid:{3EB3C877-1F16-487C-9050-104DBCD66683}"}, {"process_id": "1792", "name": "cscript.exe  //nologo m.vbs"}, {"process_id": "2604", "time_offset": 7, "name": "%SAMPLEPATH%", "children": [{"process_id": "1204", "time_offset": 187, "name": "%windir%\\tasksche.exe /i"}]}, {"process_id": "2908", "name": "%SAMPLEPATH% -m security"}, {"process_id": "2080", "name": "lhdfrgui.exe", "children": [{"process_id": "2432", "time_offset": 4, "name": "C:\\WINDOWS\\tasksche.exe /i"}]}], "calls_highlighted": ["GetTickCount64", "GetTickCount", "GetAdaptersAddresses"], "files_copied": [{"source": "C:\\WINDOWS\\tasksche.exe", "destination": "C:\\WINDOWS\\qeriuwjhrf"}], "verdicts": ["RANSOM"], "files_written": ["C:\\WINDOWS\\tasksche.exe", "C:\\Windows\\tasksche.exe", "C:\\ProgramData\\hzabcojofyn317\\tasksche.exe", "C:\\ProgramData\\hzabcojofyn317\\taskdl.exe", "C:\\ProgramData\\hzabcojofyn317\\taskse.exe", "C:\\ProgramData\\hzabcojofyn317\\@WanaDecryptor@.exe", "C:\\ProgramData\\hzabcojofyn317\\170801627321454.bat", "C:\\ProgramData\\hzabcojofyn317\\m.vbs", "C:\\Users\\<USER>\\Desktop\\@WanaDecryptor@.exe", "C:\\Users\\Default\\Desktop\\~SD60F3.tmp", "C:\\Users\\Default\\Desktop\\~SD60F4.tmp", "C:\\Users\\<USER>\\Documents\\@WanaDecryptor@.exe", "C:\\Users\\Default\\Documents\\~SD6174.tmp", "C:\\Users\\Default\\Documents\\~SD6175.tmp", "C:\\@WanaDecryptor@.exe", "C:\\System Volume Information\\@WanaDecryptor@.exe", "C:\\Users\\<USER>\\AppData\\Local\\Microsoft\\Device Metadata\\dmrccache\\downloads\\~SD76D7.tmp", "C:\\Users\\<USER>\\AppData\\Local\\VirtualStore\\~SD8770.tmp", "C:\\Users\\<USER>\\AppData\\Roaming\\Microsoft\\Windows\\Start Menu\\~SD8A72.tmp", "C:\\Users\\<USER>\\AppData\\Roaming\\Microsoft\\Windows\\Start Menu\\Programs\\~SD8A73.tmp", "C:\\Users\\<USER>\\AppData\\Roaming\\Microsoft\\Windows\\Start Menu\\Programs\\Accessories\\~SD8A74.tmp", "C:\\Users\\<USER>\\AppData\\Roaming\\Microsoft\\Windows\\Start Menu\\Programs\\Accessories\\Accessibility\\~SD8A75.tmp", "C:\\Users\\<USER>\\AppData\\Roaming\\Microsoft\\Windows\\Start Menu\\Programs\\Accessories\\System Tools\\~SD8A76.tmp", "C:\\Users\\<USER>\\AppData\\Roaming\\Microsoft\\Windows\\Start Menu\\Programs\\Administrative Tools\\~SD8A77.tmp", "C:\\Users\\<USER>\\AppData\\Roaming\\Microsoft\\Windows\\Start Menu\\Programs\\Maintenance\\~SD8A78.tmp", "C:\\Users\\<USER>\\AppData\\Roaming\\Microsoft\\Windows\\Start Menu\\Programs\\Python 3.7\\~SD8A79.tmp", "C:\\Users\\<USER>\\AppData\\Roaming\\Microsoft\\Windows\\Start Menu\\Programs\\Startup\\~SD8A7A.tmp", "C:\\Users\\<USER>\\Downloads\\~SD8B19.tmp", "C:\\Users\\<USER>\\Downloads\\calendar.xlsx.WNCRYT", "C:\\Users\\<USER>\\Downloads\\ticketinfo.doc.WNCRYT", "C:\\Users\\<USER>\\Downloads\\@Please_Read_Me@.txt", "C:\\Users\\<USER>\\Downloads\\@WanaDecryptor@.exe", "C:\\Users\\<USER>\\Downloads\\files\\~SD8B29.tmp", "C:\\Users\\<USER>\\Downloads\\__pycache__\\~SD8B2A.tmp", "C:\\ProgramData\\Microsoft\\Windows\\Start Menu\\~SD8C43.tmp", "C:\\ProgramData\\Microsoft\\Windows\\Start Menu\\Programs\\~SD8C44.tmp", "C:\\ProgramData\\Microsoft\\Windows\\Start Menu\\Programs\\7-Zip\\~SD8C45.tmp", "C:\\ProgramData\\Microsoft\\Windows\\Start Menu\\Programs\\Accessories\\~SD8C46.tmp", "C:\\ProgramData\\Microsoft\\Windows\\Start Menu\\Programs\\Accessories\\Accessibility\\~SD8C47.tmp", "C:\\ProgramData\\Microsoft\\Windows\\Start Menu\\Programs\\Accessories\\System Tools\\~SD8C48.tmp", "C:\\ProgramData\\Microsoft\\Windows\\Start Menu\\Programs\\Accessories\\Tablet PC\\~SD8C49.tmp", "C:\\ProgramData\\Microsoft\\Windows\\Start Menu\\Programs\\Accessories\\Windows PowerShell\\~SD8C5A.tmp", "C:\\ProgramData\\Microsoft\\Windows\\Start Menu\\Programs\\Administrative Tools\\~SD8C5B.tmp", "C:\\ProgramData\\Microsoft\\Windows\\Start Menu\\Programs\\Adobe\\~SD8C5C.tmp", "C:\\ProgramData\\Microsoft\\Windows\\Start Menu\\Programs\\Adobe\\Adobe Download Manager\\~SD8C5D.tmp", "C:\\ProgramData\\Microsoft\\Windows\\Start Menu\\Programs\\Games\\~SD8C5E.tmp", "C:\\ProgramData\\Microsoft\\Windows\\Start Menu\\Programs\\Graphviz 2.38\\~SD8C5F.tmp", "C:\\ProgramData\\Microsoft\\Windows\\Start Menu\\Programs\\Graphviz 2.38\\Manuals\\~SD8C60.tmp", "C:\\ProgramData\\Microsoft\\Windows\\Start Menu\\Programs\\Java\\~SD8C61.tmp", "C:\\ProgramData\\Microsoft\\Windows\\Start Menu\\Programs\\LibreOffice 6.4\\~SD8C62.tmp", "C:\\ProgramData\\Microsoft\\Windows\\Start Menu\\Programs\\Maintenance\\~SD8C63.tmp", "C:\\ProgramData\\Microsoft\\Windows\\Start Menu\\Programs\\Startup\\~SD8C64.tmp", "C:\\ProgramData\\Microsoft\\Windows\\Start Menu\\Programs\\Tablet PC\\~SD8C74.tmp", "C:\\ProgramData\\Microsoft\\Windows\\Start Menu\\Programs\\VideoLAN\\~SD8C75.tmp", "C:\\Users\\Default\\~SD8E04.tmp", "C:\\Users\\Default\\AppData\\~SD8E05.tmp", "C:\\Users\\Default\\AppData\\Local\\~SD8E06.tmp", "C:\\Users\\Default\\AppData\\Local\\Microsoft\\~SD8E07.tmp", "C:\\Users\\Default\\AppData\\Local\\Microsoft\\Windows\\~SD8E08.tmp", "C:\\Users\\Default\\AppData\\Local\\Microsoft\\Windows\\GameExplorer\\~SD8E09.tmp"], "verdict_confidence": 70, "dns_lookups": [{"hostname": "www.ifferfsodp9ifjaposdfjhgosurijfaewrwergwea.com"}, {"hostname": "www.ifferfsodp9ifjaposdfjhgosurijfaewrwergwea.com"}, {"hostname": "www.ifferfsodp9ifjaposdfjhgosurijfaewrwergwea.com"}], "files_dropped": [{"path": "%ProgramData%\\yuuaclhph815\\tasksche.exe", "sha256": "ed01ebfbc9eb5bbea545af4d01bf5f1071661840480439c6e5babe8e080e41aa"}, {"path": "%ProgramData%\\yuuaclhph815\\taskdl.exe", "sha256": "4a468603fdcb7a2eb5770705898cf9ef37aade532a7964642ecd705a74794b79"}, {"path": "C:\\WINDOWS\\tasksche.exe", "sha256": "ed01ebfbc9eb5bbea545af4d01bf5f1071661840480439c6e5babe8e080e41aa"}], "command_executions": ["%SAMPLEPATH%", "%windir%\\tasksche.exe /i"], "services_started": ["mssecsvc2.0"], "verdict_labels": ["WannaCry", "WannaCry_KillSwitch"], "memory_pattern_urls": ["http://cwwnhwhlz52maqm7.onion", "http://gx7ekbenv2riucmf.onion", "http://57g7spgrzlojinas.onion", "http://xxlvbrloxvriy2c5.onion", "http://76jdd2ir2embyv47.onion", "http://www.ifferfsodp9ifjaposdfjhgosurijfaewrwergwea.com"], "http_conversations": [{"url": "http://www.ifferfsodp9ifjaposdfjhgosurijfaewrwergwea.com/", "request_method": "GET", "request_headers": {"Host": "www.ifferfsodp9ifjaposdfjhgosurijfaewrwergwea.com", "Cache-Control": "no-cache"}}, {"url": "http://www.ifferfsodp9ifjaposdfjhgosurijfaewrwergwea.com", "request_method": "GET"}]}}