{"data": {"signals_hooked": ["android.intent.action.TIMEZONE_CHANGED", "android.intent.action.AIRPLANE_MODE", "android.net.conn.CONNECTIVITY_CHANGE", "android.intent.action.BATTERY_CHANGED", "android.intent.action.ACTION_POWER_CONNECTED", "android.intent.action.ACTION_POWER_DISCONNECTED"], "files_deleted": ["/data/data/com.truecaller/code_cache/secondary-dexes/tmp-com.truecaller-1.apk.classes-1573713886.zip", "/data/data/com.truecaller/code_cache/secondary-dexes/tmp-com.truecaller-1.apk.classes1569208693.zip", "/data/data/com.truecaller/shared_prefs/multidex.version.xml.bak", "/data/data/com.truecaller/shared_prefs/com.google.android.gms.measurement.prefs.xml.bak", "/data/data/com.truecaller/files/AppEventsLogger.persistedevents", "/data/data/com.truecaller/shared_prefs/com.crashlytics.sdk.android:answers:settings.xml.bak", "/data/data/com.truecaller/shared_prefs/tc.settings.xml.bak", "/data/data/com.truecaller/shared_prefs/com.google.android.gms.appid.xml.bak", "/data/data/com.truecaller/shared_prefs/com.truecaller_preferences.xml.bak", "/data/data/com.truecaller/shared_prefs/gcm-scheduler-engine-initial.xml.bak", "/data/data/com.truecaller/shared_prefs/com.facebook.sdk.appEventPreferences.xml.bak", "/data/data/com.truecaller/shared_prefs/com.facebook.sdk.attributionTracking.xml.bak", "/data/data/com.truecaller/shared_prefs/TwitterAdvertisingInfoPreferences.xml.bak", "/data/data/com.truecaller/shared_prefs/com.crashlytics.prefs.xml.bak", "/data/data/com.truecaller/files/.Fabric/com.crashlytics.sdk.android:answers/session_analytics.tap", "/data/data/com.truecaller/cache/disklru/journal.bkp", "/data/data/com.truecaller/files/.Fabric/com.crashlytics.sdk.android.crashlytics-core/initialization_marker", "/data/data/com.truecaller/files/.Fabric/com.crashlytics.sdk.android.crashlytics-core/log-files/crashlytics-userlog-56849AFB0243-0001-3CAA-9CCC36733B72.temp", "/data/data/com.truecaller/files/.Fabric/com.crashlytics.sdk.android.crashlytics-core/log-files/crashlytics-userlog-56849AFD00DD-0001-3CAD-EF6F5D39AFE1.temp", "/data/data/com.truecaller/code_cache/secondary-dexes/tmp-com.truecaller-1.apk.classes1748197113.zip", "/data/data/com.truecaller/code_cache/secondary-dexes/tmp-com.truecaller-1.apk.classes705844626.zip", "/data/data/com.truecaller/shared_prefs/multidex.version.xml.bak", "/data/data/com.truecaller/shared_prefs/com.google.android.gms.measurement.prefs.xml.bak", "/data/data/com.truecaller/files/AppEventsLogger.persistedevents", "/data/data/com.truecaller/shared_prefs/com.google.android.gms.appid.xml.bak", "/data/data/com.truecaller/code_cache/secondary-dexes/tmp-com.truecaller-1.apk.classes1043513851.zip", "/data/data/com.truecaller/code_cache/secondary-dexes/tmp-com.truecaller-1.apk.classes-1358075736.zip", "/data/data/com.truecaller/code_cache/secondary-dexes/tmp-com.truecaller-1.apk.classes-9718566.zip", "/data/data/com.truecaller/code_cache/secondary-dexes/tmp-com.truecaller-1.apk.classes-336909264.zip", "/data/data/com.truecaller/code_cache/secondary-dexes/tmp-com.truecaller-1.apk.classes200446278.zip", "/data/data/com.truecaller/code_cache/secondary-dexes/tmp-com.truecaller-1.apk.classes1158926755.zip", "/data/data/com.truecaller/code_cache/secondary-dexes/tmp-com.truecaller-1.apk.classes349206185.zip", "/data/data/com.truecaller/code_cache/secondary-dexes/tmp-com.truecaller-1.apk.classes1265145320.zip", "/data/data/com.truecaller/code_cache/secondary-dexes/tmp-com.truecaller-1.apk.classes973863240.zip", "/data/data/com.truecaller/code_cache/secondary-dexes/tmp-com.truecaller-1.apk.classes-1395577478.zip", "/data/data/com.truecaller/code_cache/secondary-dexes/tmp-com.truecaller-1.apk.classes554949328.zip", "/data/data/com.truecaller/code_cache/secondary-dexes/tmp-com.truecaller-1.apk.classes-889815587.zip", "/data/data/com.truecaller/code_cache/secondary-dexes/tmp-com.truecaller-1.apk.classes77493471.zip", "/data/data/com.truecaller/code_cache/secondary-dexes/tmp-com.truecaller-1.apk.classes-1341913348.zip", "/data/data/com.truecaller/code_cache/secondary-dexes/tmp-com.truecaller-1.apk.classes2010398187.zip", "/data/data/com.truecaller/code_cache/secondary-dexes/tmp-com.truecaller-1.apk.classes-305569047.zip"], "services_bound": ["\ncom.google.android.gms.ads.identifier.service.START\n", "\ncom.google.android.gms.clearcut.service.START\n", "\ncom.google.android.gms.config.START\n", "com.truecaller/com.truecaller.presence.PresenceService\ncom.truecaller.androidactors.ActorService\n", "com.truecaller/com.truecaller.analytics.EventsTrackerService\ncom.truecaller.androidactors.ActorService\n", "\ncom.google.android.gms.measurement.START\n"], "files_opened": ["/data/app/com.truecaller-1.apk", "/data/data/com.truecaller/code_cache/secondary-dexes/MultiDex.lock", "/data/data/com.truecaller/code_cache/secondary-dexes/tmp-com.truecaller-1.apk.classes1748197113.zip", "/data/data/com.truecaller/code_cache/secondary-dexes/com.truecaller-1.apk.classes2.zip", "/data/data/com.truecaller/code_cache/secondary-dexes/tmp-com.truecaller-1.apk.classes705844626.zip", "/data/data/com.truecaller/code_cache/secondary-dexes/com.truecaller-1.apk.classes3.zip", "/data/data/com.truecaller/shared_prefs/multidex.version.xml", "/data/data/com.truecaller/code_cache/secondary-dexes/com.truecaller-1.apk.classes2.dex", "/data/data/com.truecaller/code_cache/secondary-dexes/com.truecaller-1.apk.classes3.dex", "/data/misc/keychain/pins", "/data/data/com.truecaller/shared_prefs/com.google.android.gms.measurement.prefs.xml", "/data/data/com.truecaller/no_backup/com.google.InstanceId.properties", "/system/etc/security/cacerts/81b9768f.0", "/data/data/com.truecaller/shared_prefs/com.google.android.gms.appid.xml", "/proc/net/if_inet6", "/sys/class/net/lo/ifindex", "/sys/class/net/sit0/ifindex", "/sys/class/net/eth0/ifindex", "/sys/class/net/ip6tnl0/ifindex", "/sys/class/net/eth0/mtu", "/data/data/com.truecaller/code_cache/secondary-dexes/tmp-com.truecaller-1.apk.classes1043513851.zip", "/data/data/com.truecaller/code_cache/secondary-dexes/tmp-com.truecaller-1.apk.classes-1358075736.zip", "/data/data/com.truecaller/code_cache/secondary-dexes/tmp-com.truecaller-1.apk.classes-9718566.zip", "/data/data/com.truecaller/code_cache/secondary-dexes/tmp-com.truecaller-1.apk.classes-336909264.zip", "/data/data/com.truecaller/code_cache/secondary-dexes/tmp-com.truecaller-1.apk.classes200446278.zip", "/data/data/com.truecaller/code_cache/secondary-dexes/tmp-com.truecaller-1.apk.classes1158926755.zip", "/data/data/com.truecaller/code_cache/secondary-dexes/tmp-com.truecaller-1.apk.classes349206185.zip", "/data/data/com.truecaller/code_cache/secondary-dexes/tmp-com.truecaller-1.apk.classes1265145320.zip", "/data/data/com.truecaller/code_cache/secondary-dexes/tmp-com.truecaller-1.apk.classes973863240.zip", "/data/data/com.truecaller/code_cache/secondary-dexes/tmp-com.truecaller-1.apk.classes-1395577478.zip", "/data/data/com.truecaller/code_cache/secondary-dexes/tmp-com.truecaller-1.apk.classes554949328.zip", "/data/data/com.truecaller/code_cache/secondary-dexes/tmp-com.truecaller-1.apk.classes-889815587.zip", "/data/data/com.truecaller/code_cache/secondary-dexes/tmp-com.truecaller-1.apk.classes77493471.zip", "/data/data/com.truecaller/code_cache/secondary-dexes/tmp-com.truecaller-1.apk.classes-1341913348.zip", "/data/data/com.truecaller/code_cache/secondary-dexes/tmp-com.truecaller-1.apk.classes2010398187.zip", "/data/data/com.truecaller/code_cache/secondary-dexes/tmp-com.truecaller-1.apk.classes-305569047.zip"], "calls_highlighted": ["android.util.Base64.decode", "android.util.Base64.encode"], "tags": ["REFLECTION", "RUNTIME_MODULES"], "invokes": ["dalvik.system.DexPathList.makeDexElements", "android.content.pm.IPackageManager$Stub$Proxy.getServiceInfo", "android.content.pm.IPackageManager$Stub$Proxy.getApplicationInfo", "android.content.pm.IPackageManager$Stub$Proxy.checkPermission", "android.content.pm.IPackageManager$Stub$Proxy.queryIntentServices", "com.google.firebase.iid.FirebaseInstanceId.getInstance", "android.net.NetworkInfo$State.values", "com.google.android.gms.measurement.AppMeasurement.getInstance", "android.content.pm.IPackageManager$Stub$Proxy.getProviderInfo", "android.content.pm.IPackageManager$Stub$Proxy.getActivityInfo", "android.content.pm.IPackageManager$Stub$Proxy.resolveContentProvider", "com.google.android.gms.common.GooglePlayServicesUtil.isGooglePlayServicesAvailable", "android.content.pm.IPackageManager$Stub$Proxy.getInstallerPackageName"], "modules_loaded": ["/data/data/com.truecaller/code_cache/secondary-dexes/com.truecaller-1.apk.classes2.zip", "/data/data/com.truecaller/code_cache/secondary-dexes/com.truecaller-1.apk.classes3.zip", "/system/framework/com.android.media.remotedisplay.jar", "/system/framework/com.android.location.provider.jar", "/system/priv-app/GmsCore.apk"], "activities_started": ["com.truecaller/com.truecaller.ui.WizardActivity\n\n", "com.truecaller.ui.TruecallerInit (com.truecaller)", "com.koushikdutta.superuser.RequestActivity (com.thirdparty.superuser)", "com.koushikdutta.superuser.MultitaskSuRequestActivity (com.thirdparty.superuser)"], "ip_traffic": [{"transport_layer_protocol": "TCP", "destination_ip": "185.60.216.15", "destination_port": 443}, {"transport_layer_protocol": "TCP", "destination_ip": "179.60.195.7", "destination_port": 443}, {"transport_layer_protocol": "TCP", "destination_ip": "179.60.192.3", "destination_port": 443}, {"transport_layer_protocol": "TCP", "destination_ip": "157.240.21.16", "destination_port": 443}], "processes_tree": [{"process_id": "8145", "name": "zygote", "children": [{"process_id": "15530", "name": "com.truecaller"}]}, {"process_id": "8145", "name": "zygote", "children": [{"process_id": "15533", "name": "com.truecaller"}]}], "permissions_checked": [{"owner": "com.google.android.gms", "permission": "com.google.android.c2dm.permission.SEND"}], "encoding_algorithms_observed": ["base64"], "text_decoded": ["0\ufffd\u0001\"0\r\u0006\t*\ufffdH\ufffd\ufffd\r\u0001\u0001\u0001\u0005\u0000\u0003\ufffd\u0001\u000f\u00000\ufffd\u0001\n\u0002\ufffd\u0001\u0001\u0000\ufffd\ufffdeI\ufffd` _O\ufffdx\ufffd&J#\ufffd\ufffd\u03ac\ufffd5\ufffd2\ufffdo\ufffd\u3591\ufffdz\ufffdm\ufffd\ufffdu\u0012\ufffd\u0006\u0003+\u5238a\ufffdR\ufffd?U\ufffd\ufffd\ufffdL\ufffd\ufffd\ufffd\u0001\ufffd^\ufffd\ufffd\u001d\t\ufffd\u0004p)\ufffd\ufffdY\ufffd\u001aF9\ufffd\ufffd\ufffdk\u001e|\ufffd\u031b\ufffdt\ufffd\ufffdb%\u0002\ufffd\ufffdk\ufffd\u001d\fN\ufffd-\u07ee\ufffdd\ufffdS\u0456t\ufffd\ufffd\u010b\ufffd\"A\u007f\ufffd]\ufffd;.\u001dX\ufffd\ufffd\u0353B\ufffdB\ufffd\ufffd.!\ufffdok\ufffd\ufffd+\ufffdh0o\ufffd~\ufffd1Wj\ufffd\ufffdo<Bg\ufffd\ufffdNv\u0001^\u0019p\\h\ufffd\ufffdh\ufffd\ufffd\ufffdc\ufffd\u001fIa\ufffdf\ufffd\ufffd\ufffd%\u0010k\ufffdS\ufffd\ufffd\ufffd\t\ufffdO\ufffd\ufffdE\ufffd\ufffd\ufffd\u001d\ufffdF\ufffda\ufffd\u0001\ufffd\ufffd\ufffd\ufffd\ufffdB\ufffd\ucff3\ufffd\u9255h\ufffd\ufffd`b@\u0003\ufffd\ufffd\ufffd\ufffdZ\ufffd\ufffdO+\ufffd\ufffd\ufffd\ufffdC\ufffd+\ufffd\ufffdA\u0002\u0003\u0001\u0000\u0001", "z4\ufffd\u000e\u07de\ufffdRe\ufffd+[\ufffd\u0016\ufffd8\ufffd\ufffd_\ufffd", "\n0x00000"], "shared_preferences_sets": [{"key": "timestamp", "value": "1528355750000"}, {"key": "crc", "value": "924146070"}, {"key": "dex.number", "value": "3"}, {"key": "dex.crc.2", "value": "3937930654"}, {"key": "dex.time.2", "value": "1528355755000"}, {"key": "dex.crc.3", "value": "2080821794"}, {"key": "dex.time.3", "value": "1528355756000"}, {"key": "has_been_opened", "value": "true"}, {"key": "|S||P|", "value": "MIIBIjANBgkqhkiG9w0BAQEFAAOCAQ8AMIIBCgKCAQEAyYOPElixkUiVVHSf_eVm7jCia8CmRJoRUXnaIAQR097H5gJd90GV-Jq-5ZryX3FHMzZ-EeDYnL4R6ZapKO0oYA4lTpJ-Z7TvVUCMKysNyFq41ZqIdChNys2OAbZ_MChKATd3hvP32uH_I_L4dwmACt59bBmlJs7BXeOrePK10_rhvuFcRF22xeauQp2aCmAlHi1IJe8mFZGjkChFPIJvT15XPjzpyVf7uSLrFgBl-rVoVo-irZUbenTWip55vgp-E0axOh8qvnKOiN-dAkkk7qDpGVFInLcPrXHXJ79fht6vhSGFFem3YHAXtUX_Y1YiwncLZiTy_iTCi6xDC3Dj8QIDAQAB"}, {"key": "|S||K|", "value": "MIIEvgIBADANBgkqhkiG9w0BAQEFAASCBKgwggSkAgEAAoIBAQDJg48SWLGRSJVUdJ_95WbuMKJrwKZEmhFRedogBBHT3sfmAl33QZX4mr7lmvJfcUczNn4R4NicvhHplqko7ShgDiVOkn5ntO9VQIwrKw3IWrjVmoh0KE3KzY4Btn8wKEoBN3eG8_fa4f8j8vh3CYAK3n1sGaUmzsFd46t48rXT-uG-4VxEXbbF5q5CnZoKYCUeLUgl7yYVkaOQKEU8gm9PXlc-POnJV_u5IusWAGX6tWhWj6KtlRt6dNaKnnm-Cn4TRrE6Hyq-co6I350CSSTuoOkZUUictw-tcdcnv1-G3q-FIYUV6bdgcBe1Rf9jViLCdwtmJPL-JMKLrEMLcOPxAgMBAAECggEBALiHVUNanrfIfJ5K8ZtBL4FcXc9IKblWUBeI-roon96g-fJhJoTdtSRjJ_3_ZoUJqUZ3VviuKg1Wa_a4NQ06JqfXLEiIE2KKKEOsCO8azNM0aF-J0_xyT9IvayOcZ1nE-wekMDsPO19fZhEYVHhE5dCOLtIHpdkkqaN9cS8fKmwCh_Okpy_0hx_cJY49AOSY40aD-8JUQycotHtI1q3yd57ue9Nx6QcdopERNQkS-vN9lAN6BJjdz97T4AQLh-h7m6OATVmBIN6AhQlTp2RMYHRdvvkdaUHnjN-zLF3bDIhTaT4Oy47JTduDE0VMMP3Taybltnnjfp3zRSIOJYUU59UCgYEA6ss5ZWIQ1ySMgtvb9bFWQlnh2d3Cu8Q5I01JyJkVLFHYIIB2WWh9LjKhMHHMceSeNG7pHvK1oxSLBv9c-LzXM1lFEleaT32hwMUCla6zFdM-95jk-FSU1OeJFAcW1RzAiCpmCa9VnbKyV-s5PIdrpky6Nvpfif7PZ-xaWfIbGNcCgYEA27bamXdFDvG552DTHBFMXRovLF_3vE_jLo0LcqyttvG96aSAkuzEqjx3nDvnzSNXj-dnJHNqbZCM7do3ebFyImF3gmP4K7GhTFSQHlT02ngDKDki-slSkeZZmW8f-tURl8wh99e8iFQcFkV1xzs6W6eudyXgh5KE4e4ogTonaHcCgYAYZcmvCUOqt3eKWYI_w4-tEV3wn6SOklNFodBa8d1LX63PosmpfLwVQtmRCSIva4ws8qFyv9G0Anx3260zg5vxEAOnZkb4n5thRpeAKkkdqXfPjqmsTE2y2eRammn69yPiglVcCEYjPuBdVmn6KjA7dZmcAORQmJPAvsScuBWsvQKBgGxX7dGxc7db0b1cDJ4RlaNvbwWlySbuCewBlzyUFBFbgbe9670Hzi7YJG9BRxvsKpiGlmDuHPQsTKJZcfOrYcm8YE9G9rCtJgnaxTp_0EIO3heunSYnsnTJrzMvDgkFmmhNPA7YLlrXhwYgeGSnOy7JMAoG_oI76RTz-LtIrvgfAoGBAIjy0TO6yIdreY3nv23SL6GmxonPr4I_QZHr1TTQU3NRecKGC7I3CAmKzt9h0E0v2SaRviqTr1qNyG6tmUgFvoFihzZvjSnamkkUQvYrcaa0TP1pN4G0udfj8O3bHejrrTJZTtNlBeZMJjtGvQ3qA9MxLVa0b2ftMKyOj9EM-jSg"}, {"key": "|S|cre", "value": "1528355760472"}, {"key": "timestamp", "value": "1528451094000"}, {"key": "dex.time.2", "value": "1528451098000"}, {"key": "dex.time.3", "value": "1528451099000"}, {"key": "timestamp", "value": "1528355706000"}, {"key": "dex.time.2", "value": "1528355711000"}, {"key": "dex.time.3", "value": "1528355712000"}, {"key": "|S||P|", "value": "MIIBIjANBgkqhkiG9w0BAQEFAAOCAQ8AMIIBCgKCAQEAmfqToLpb9vMm0LTe69NWNSrn9mK7sj6EfyF7FyaH2T8J3rSBbnEZbcnCxMyCX5-pzUMQrZEBFSTUuBy0WhQ5hM2OhdV3Z5qeSjTRbDR2weLBg3M4QHznspxphSlPLg14A3T0Iu2qAvpSQwxKuZiH7q7_IZ_EMWvSR8C5eAThU7XxPSHkeGX4dw6-6YZ7VwFgDX66uvdR_Wfn3O6mvkYeu0whk_gfUnNHWDO8JFzUGpsukyLUMnyJLJ4YR54fDIyuXPVUS5W8aEa_4Tojl_5VomJdlwb_mmbxN69FFYPDapXn-CH6ONQMZ5_S5u8DCqRcoaMVP0rdqtlCOsKp7PrX8QIDAQAB"}, {"key": "|S|cre", "value": "1528355715138"}, {"key": "|S||K|", "value": "MIIEvAIBADANBgkqhkiG9w0BAQEFAASCBKYwggSiAgEAAoIBAQCZ-pOgulv28ybQtN7r01Y1Kuf2YruyPoR_IXsXJofZPwnetIFucRltycLEzIJfn6nNQxCtkQEVJNS4HLRaFDmEzY6F1Xdnmp5KNNFsNHbB4sGDczhAfOeynGmFKU8uDXgDdPQi7aoC-lJDDEq5mIfurv8hn8Qxa9JHwLl4BOFTtfE9IeR4Zfh3Dr7phntXAWANfrq691H9Z-fc7qa-Rh67TCGT-B9Sc0dYM7wkXNQamy6TItQyfIksnhhHnh8MjK5c9VRLlbxoRr_hOiOX_lWiYl2XBv-aZvE3r0UVg8Nqlef4Ifo41Axnn9Lm7wMKpFyhoxU_St2q2UI6wqns-tfxAgMBAAECggEASZHZEXWZVS-uPw_8Zu7uBK9Ab4-TIMIQKnIDzvbg96LQA3F5Whx9yuAYyFDyhd_SkLlXcaaTvtd_L4y_ez6okNRqIXXx_DV7JfeAjFOw3kiKr1TQ7rb_OW7UWAR5yYYz7mrl7v5hOdUCkvh_h5fict94FUexxO9AZHon47lpM8ZAAMjZ7QgqzIvXVUv9WZsbr8Maf9h23971sjVUAnXXZlMouqOctW3Jkp5tfsRn-JU0MF4x_NH9x7-Rsr3ahrIiCsWSvJNouLtOX3_RoVtFsJ0YbInRnMgY8EbcS-ePEqvyL2XDVnS4w3wciNsev5yu5INWIfwdPO7Z50PIvT3qQQKBgQDKHvmlXu7rN41hkyxuN3yrHyn68SEJV1d9VwCbWcMFqT2V9hHP4jFzyfmjZgKgEFhggEvHd1o0C_Sg698aeGaGfOsPFAxqzgRsnPjTHsil4fTQHmpxSWh7KdX39-YggzdFCvwPCbHkNw7nUsfCzn_gB9kL1z1Q16KQbQHFh_dXWQKBgQDDBk93gNoVS40B7Puo3KOPC_PiLNF-xqtg3-rnQBl83At2d-e8-UhupE8bV385Yw_flLR7EVISmOvGM1aW_VRym7yfklDwHdXs2n68Z71LINoMs5iOjoZ6wphG0oyhpqsgtDKohv7HnFIIsz9lfjJ6pSrrZlFU3P2nwUvqtLQKWQKBgF6QW3CZl-KI3SbXuqPeZf-R1wxHIJPEP3Su7ePA_VN6uQueUvsV8tkfmCJwqa3Ft_N-UvYByzwqk8tuT7WMuzsU2sz1LlISDVPbpTbxYiLqMqXkdRyHodBt5GPdodd4TLWKzB8lBAuoDtr_ieKExqNESLIXg-J84Nv9hCSs1nYRAoGAIUgCZ7JlhRzPg3SdvcNpZg_0HrTnS2s789xCihQ2RUiH7D-qHGWuJrODjHbyDykInG8UHaxnBSVzlu9L55hzwNsy5Uhi55cv2quu1RgfBaMlkuVTM4C_ElQDCJMFzNBUg9A8lOX0tLvIhBOSzg8rLiLhoCpl1sWfw_EIs5UC5IECgYBgJWZioeyc11zTubnR1EntODtxLB7C3adtcLAyUYh08w0ADQeQ6lzyVF59EMvWr0a0wEbYORB_JBI67Z3tPdRRRY6-GOBy1glf1qc13_FOHMNPxvFoTUwjYCTz6Qn5Hu8uyaQrrbLJuPBwFt-prChPZPJU-KpWCGtD5-Zxdi0UPw"}, {"key": "timestamp", "value": "1527503740000"}, {"key": "dex.time.2", "value": "1527503757000"}, {"key": "dex.time.3", "value": "1527503758000"}, {"key": "|S||P|", "value": "MIIBIjANBgkqhkiG9w0BAQEFAAOCAQ8AMIIBCgKCAQEAn94JbMZR2QRRQWjr0L_wpOVjEAZ-LsV3WNsQDjz2L48RrDPszooXp219M_Nqv7QAmzRh4dPwpguqVj4zuqMXBWLOlAPNBH9fRz2ZA7aQ42VyBjdrqlA1k_4HZh5EWBgefgb_Z2Oa6G5k-q1qcRoCrUwDw0PwwqoinkkFUVo2trOZBg-owbnAGZtz3BOM5zw-_TmCH9HcBH_ScAu5bIRpCGyio45KqEdIAyLBDv4ZcbPcJVN37dTLvRMHPebOe5JtHsk2AY-he8RRh_nnafNu3We1aeWrEJH5pu6-u7isdkZGZu1di-nyAFh00-Me2i9y4g5DvwMeG2u4yUfTjyQI9QIDAQAB"}, {"key": "|S||K|", "value": "MIIEvQIBADANBgkqhkiG9w0BAQEFAASCBKcwggSjAgEAAoIBAQCf3glsxlHZBFFBaOvQv_Ck5WMQBn4uxXdY2xAOPPYvjxGsM-zOihenbX0z82q_tACbNGHh0_CmC6pWPjO6oxcFYs6UA80Ef19HPZkDtpDjZXIGN2uqUDWT_gdmHkRYGB5-Bv9nY5robmT6rWpxGgKtTAPDQ_DCqiKeSQVRWja2s5kGD6jBucAZm3PcE4znPD79OYIf0dwEf9JwC7lshGkIbKKjjkqoR0gDIsEO_hlxs9wlU3ft1Mu9Ewc95s57km0eyTYBj6F7xFGH-edp827dZ7Vp5asQkfmm7r67uKx2RkZm7V2L6fIAWHTT4x7aL3LiDkO_Ax4ba7jJR9OPJAj1AgMBAAECggEAJHr7dZnv1XDZxe5WWYVjOY2qxF5m7u9ao6khic45c3LXWo9iy2LRsQAYIQG761D9Dm2upGTDtnBVB2ccUMukljMM5tPTNeKG8G_K-gDwISPmGCsPY4b4IvRF5fSkLeIbGzEnmQUutTlzy4xFDNgdokQFW8qmJxXB3pLVJtJKR_hpVOxcDaqyg7_yYgPOb9xM5Bgb3GaFuFC9sVud1YYr7pifH2c7EviKmMHHe-53101aA3JkZ9H-HnoTrLVjrCVfK70Y0dTQQ2tJTB-f094FWXOLTPjg4iXizda1QaTjEWJxS9UXa-GsRWd80azHmEf4Pf4EyPox2v6E1s6oHgMbIQKBgQDULmM-8LgZA1SPgRBjKkaG95dWx17BEGEN_jdHB7Jeffu-DgwN2CeLFKKRMMvIOYxocVaATW5u9JeyxXdZqLzRKtLIqlD0Hl4SMCyhIlKLlVH5NgxJ30GQLWqUWeVfBaGnW1z7myk3GxLJj8Rw-6CZ0DYks5RFfhKd_NPE-8YDSQKBgQDA4epUYlweSg0QqFksYUe8S3U32Z2bdhtGb-yqYmyBooQ9t5Ws6lr5SOCgM4w9-42SmsQweMyO3MfGxWn9OlioyiOBpN09ZFKikbJDXH94QGr4VE1FaN20eTMKqAqDVwr5so-Oe2PcuC_6BfifBumiCTH14Do6bHygnyruF2CsTQKBgQCgYhf-wXJG5e-LMaGzc4cwCgLJQ5ZqFPln3FroQ_cd2djqRi_yXws04_omCV5gELADWnhqLx1knVn1dbHLgfKHoPkHWUYr4LB2yxdRDWKbw9jcqXAMfsdONiYz0OfCNb2FhVf5j8VNtBc1aIiyZmF1Ip9qiptvE-b6qNtiMHXykQKBgFOfXlV5U1C6cBGhuw93mX80A7zT9vWYbdjK24M_KqXFTKnpNtYBwLFE_EXYM1wH_Gfr-1S8eosRgvdVTU9BBYEgKeaiEFz2arEak3uK1aTP4NCK0_lcron45b0f_3bTvOlmlcCDFFdz7zDpd9GSUKY0cFmV_gioUhvdBeK1de8dAoGAML97nrZAGead1ugXv5wcbs5J11sZOGDLBSoGoAOhF9PV4zqTGs88--RCXwkG2G9Vmd8plJ_bIMHUrSqP1Ldx4He1p7adjt7TeKVR5gXt203_Fqmp4U1mlTlsgJeiQuUykNTtdj2LmKT7yLEXetEMDQzb-ba2PEwVjTwfmDfnI24"}, {"key": "|S|cre", "value": "1527503763399"}, {"key": "analytics_launched", "value": "true"}, {"key": "timestamp", "value": "1527503669000"}, {"key": "dex.time.2", "value": "1527503674000"}, {"key": "dex.time.3", "value": "1527503675000"}, {"key": "timestamp", "value": "1528451056000"}, {"key": "dex.time.2", "value": "1528451066000"}, {"key": "dex.time.3", "value": "1528451067000"}, {"key": "timestamp", "value": "1527503828000"}, {"key": "dex.time.2", "value": "1527503834000"}, {"key": "dex.time.3", "value": "1527503835000"}, {"key": "|S||P|", "value": "MIIBIjANBgkqhkiG9w0BAQEFAAOCAQ8AMIIBCgKCAQEA8akR8ELrE69N6KiK6GT0El3r4gUPEfGibmp-eX44AmLkIiX1lLF9BgvEi9vekXSz6S3rzyAP3NwkWnz-VdavtK3_ZTTpyVbef9HnwAfhIqWoKHURBZBsvBU0e9k3pEAa4MRZjf7ldxypIXpAuM_OABWMpaTsujThM_sGV6hyrcVfxjCyBRsNP3YBTlut7tEo62AGLBi59yMVm-i5QzVDBZX9Jc8v6H372oF29H_qZ-u32bckJDGFKHwULcnHdnYexeHZajX7dFBJJgyZ26nwEhAZybI33YIRUi7UdP_Xq1miuwkR_uHp2EyNZ71OfGXbAbiLi30qucRSdk3P2Dcs5wIDAQAB"}, {"key": "timestamp", "value": "1528355695000"}, {"key": "dex.time.2", "value": "1528355701000"}, {"key": "dex.time.3", "value": "1528355702000"}, {"key": "timestamp", "value": "1548940519000"}, {"key": "dex.time.2", "value": "1548940524000"}, {"key": "dex.time.3", "value": "1548940525000"}, {"key": "timestamp", "value": "1560762134000"}, {"key": "dex.time.2", "value": "1560762141000"}, {"key": "dex.time.3", "value": "1560762142000"}, {"key": "timestamp", "value": "1562012939000"}, {"key": "dex.time.2", "value": "1562012947000"}, {"key": "dex.time.3", "value": "1562012948000"}, {"key": "|S||P|", "value": "MIIBIjANBgkqhkiG9w0BAQEFAAOCAQ8AMIIBCgKCAQEAz6kpVxErC6OFRY7FS1ONeh23buqYiJL06cXgVCHHCnA9wiOh1ZvcYfT2nKW4fssAOQlho3BACf-v7tsihBDqvNiJexkO_d6Oqg4Pfd0bnvjy8wn_Jj9TNHCmYqLUu5lNN7Qw3DioCP-aisEyKKREbDqOW9OAtgwxsQDg2YjEAcupV7APHKVRemziOOTPBTFaW1yPdyVtRMK-jTQQkbzXMeoCrq4Ff-19fI3_gMPwN3E3ektcxpwSHVzRbJWKFcpMngpO3_bnutZKiQ5YnbL5DtU_WJJ3QExfjq8Kx33yotPiTSOnFgRtUUxeb8_Oezwm0xOk_yJ6ZcAtD4j_d9Z_0QIDAQAB"}, {"key": "|S||K|", "value": "MIIEvQIBADANBgkqhkiG9w0BAQEFAASCBKcwggSjAgEAAoIBAQDPqSlXESsLo4VFjsVLU416Hbdu6piIkvTpxeBUIccKcD3CI6HVm9xh9Pacpbh-ywA5CWGjcEAJ_6_u2yKEEOq82Il7GQ793o6qDg993Rue-PLzCf8mP1M0cKZiotS7mU03tDDcOKgI_5qKwTIopERsOo5b04C2DDGxAODZiMQBy6lXsA8cpVF6bOI45M8FMVpbXI93JW1Ewr6NNBCRvNcx6gKurgV_7X18jf-Aw_A3cTd6S1zGnBIdXNFslYoVykyeCk7f9ue61kqJDlidsvkO1T9YkndATF-OrwrHffKi0-JNI6cWBG1RTF5vz857PCbTE6T_InplwC0PiP931n_RAgMBAAECggEAHlLTaJVnNcHhGjEo-kDvLd_dA2NadscO4Hw2r9Jm4E1Xl1vgq_KgkeVVhbZlZI58L9gA2_7uOweNR1HUjnhx7rWoDcOw_r1bE9YNyRFakTJFN9xD1-_zVHsGsOyaJ_LQ5ct4PxA-6WF5zb08d9bU7wD1_M67wtmw_-ni66EfDivN6tqcxIHTinv747PJZGQr7iFY2GAheSZHDUIEbFnIxIvuqCUulCEy7Rmf8XIGraOmS4PT5JBCEF68YwsPmlhjQo5EX63yy_o59wfVXaA_u3E2YXhbVVbWOzP_Naoh6IfMMcZrnWNa1UUbur_rmax3acPaIrFx4Be3f2m_1QqR4QKBgQDrKNBJY2OsXd2WV0315ZrwMFcYBzXcP-QrDCzUIP8tX8xPfL9rCzIa6le9Z4BQkgrY4PmmjO--kgPOulSC9OzrVB_5wzbKecPH4rV5HUPCAssNNIoxEPBGQdIa185J0JP_GbTHeMxE0VTzZtob5BvNQJezonYRzIeZ5Sw7qk0_FQKBgQDiEHi9j8cS8JhT99qoU36m4hDjus94X-FoBUDB98VItV4VGVN8aDgDVQvN66EIP6IT7zzcyegR1DGq2rcWEicB3z96_fqhkB5jlfs8jbZ-sUcVjZ9kQqs80tJ-XRzCKa1iOPsPqai3poq7V9QyafhbHhYv_xy-lhNLw_uFZm4MzQKBgHYZJCmHGZqJ9Wu4YrW4Xsx7anHtxRXcnGkmDyllfOG7t66_tp46nCo6QGAlp6JPBdWPfrEvHIP3bqQWnbS67nTs5bYYXN7osfMjnwG5ObsojfMOzMwBdrnB-pNyh-44Kus1bL20o9l3y5MFt0nEkFXPN6CGWYds0Tjvh_xa9bpVAoGBAOENvOYaqPk2BLAzY7-Hv-Kr1FyiscEI0wIXmKyB2inURWGD4RVNO9Y1aJcMKThpARYPaev0JdD6CqgpLXQPhj3a3vu2tTj6nQZPXdqeyju-iSHv5-qMZKUczOl4ERVLII1UZLznDkwmxJ5Vha7ayKENhtEpjJhAF92pslDP9GdRAoGAHIJMkJMZ4-Q6_idAsVHdtlueEMaG4NjHs1UTYG1XTFyB3CcTXd6pi5oNGtXngq6hhD_Br-RRZOxXp-98IOUAXlePsHRYQRW18JNbkKCpNirte2OrzxBjdebbx6GPV5Z_4jTzUjp4apjcohqxgTsbDHDdIbr4iq4TQPKLaXkdUg8"}, {"key": "|S|cre", "value": "1562012952777"}, {"key": "timestamp", "value": "1562721003000"}, {"key": "dex.time.2", "value": "1562721015000"}, {"key": "dex.time.3", "value": "1562721017000"}], "files_copied": [{"source": "/data/data/com.truecaller/code_cache/secondary-dexes/tmp-com.truecaller-1.apk.classes1748197113.zip", "destination": "/data/data/com.truecaller/code_cache/secondary-dexes/com.truecaller-1.apk.classes2.zip"}, {"source": "/data/data/com.truecaller/code_cache/secondary-dexes/tmp-com.truecaller-1.apk.classes705844626.zip", "destination": "/data/data/com.truecaller/code_cache/secondary-dexes/com.truecaller-1.apk.classes3.zip"}, {"source": "/data/data/com.truecaller/code_cache/secondary-dexes/tmp-com.truecaller-1.apk.classes1043513851.zip", "destination": "/data/data/com.truecaller/code_cache/secondary-dexes/com.truecaller-1.apk.classes2.zip"}, {"source": "/data/data/com.truecaller/code_cache/secondary-dexes/tmp-com.truecaller-1.apk.classes-1358075736.zip", "destination": "/data/data/com.truecaller/code_cache/secondary-dexes/com.truecaller-1.apk.classes3.zip"}, {"source": "/data/data/com.truecaller/code_cache/secondary-dexes/tmp-com.truecaller-1.apk.classes-9718566.zip", "destination": "/data/data/com.truecaller/code_cache/secondary-dexes/com.truecaller-1.apk.classes2.zip"}, {"source": "/data/data/com.truecaller/code_cache/secondary-dexes/tmp-com.truecaller-1.apk.classes-336909264.zip", "destination": "/data/data/com.truecaller/code_cache/secondary-dexes/com.truecaller-1.apk.classes3.zip"}, {"source": "/data/data/com.truecaller/code_cache/secondary-dexes/tmp-com.truecaller-1.apk.classes200446278.zip", "destination": "/data/data/com.truecaller/code_cache/secondary-dexes/com.truecaller-1.apk.classes2.zip"}, {"source": "/data/data/com.truecaller/code_cache/secondary-dexes/tmp-com.truecaller-1.apk.classes1158926755.zip", "destination": "/data/data/com.truecaller/code_cache/secondary-dexes/com.truecaller-1.apk.classes3.zip"}, {"source": "/data/data/com.truecaller/code_cache/secondary-dexes/tmp-com.truecaller-1.apk.classes349206185.zip", "destination": "/data/data/com.truecaller/code_cache/secondary-dexes/com.truecaller-1.apk.classes2.zip"}, {"source": "/data/data/com.truecaller/code_cache/secondary-dexes/tmp-com.truecaller-1.apk.classes1265145320.zip", "destination": "/data/data/com.truecaller/code_cache/secondary-dexes/com.truecaller-1.apk.classes3.zip"}, {"source": "/data/data/com.truecaller/code_cache/secondary-dexes/tmp-com.truecaller-1.apk.classes973863240.zip", "destination": "/data/data/com.truecaller/code_cache/secondary-dexes/com.truecaller-1.apk.classes2.zip"}, {"source": "/data/data/com.truecaller/code_cache/secondary-dexes/tmp-com.truecaller-1.apk.classes-1395577478.zip", "destination": "/data/data/com.truecaller/code_cache/secondary-dexes/com.truecaller-1.apk.classes3.zip"}, {"source": "/data/data/com.truecaller/code_cache/secondary-dexes/tmp-com.truecaller-1.apk.classes554949328.zip", "destination": "/data/data/com.truecaller/code_cache/secondary-dexes/com.truecaller-1.apk.classes2.zip"}, {"source": "/data/data/com.truecaller/code_cache/secondary-dexes/tmp-com.truecaller-1.apk.classes-889815587.zip", "destination": "/data/data/com.truecaller/code_cache/secondary-dexes/com.truecaller-1.apk.classes3.zip"}, {"source": "/data/data/com.truecaller/code_cache/secondary-dexes/tmp-com.truecaller-1.apk.classes77493471.zip", "destination": "/data/data/com.truecaller/code_cache/secondary-dexes/com.truecaller-1.apk.classes2.zip"}, {"source": "/data/data/com.truecaller/code_cache/secondary-dexes/tmp-com.truecaller-1.apk.classes-1341913348.zip", "destination": "/data/data/com.truecaller/code_cache/secondary-dexes/com.truecaller-1.apk.classes3.zip"}, {"source": "/data/data/com.truecaller/code_cache/secondary-dexes/tmp-com.truecaller-1.apk.classes2010398187.zip", "destination": "/data/data/com.truecaller/code_cache/secondary-dexes/com.truecaller-1.apk.classes2.zip"}, {"source": "/data/data/com.truecaller/code_cache/secondary-dexes/tmp-com.truecaller-1.apk.classes-305569047.zip", "destination": "/data/data/com.truecaller/code_cache/secondary-dexes/com.truecaller-1.apk.classes3.zip"}], "files_written": ["/data/data/com.truecaller/code_cache/secondary-dexes/tmp-com.truecaller-1.apk.classes-1573713886.zip", "/data/data/com.truecaller/code_cache/secondary-dexes/tmp-com.truecaller-1.apk.classes1569208693.zip", "/data/data/com.truecaller/shared_prefs/multidex.version.xml", "/data/data/com.truecaller/shared_prefs/com.google.android.gms.measurement.prefs.xml", "/data/data/com.truecaller/shared_prefs/com.crashlytics.sdk.android:answers:settings.xml", "/data/data/com.truecaller/shared_prefs/tc.settings.xml", "/data/data/com.truecaller/no_backup/com.google.InstanceId.properties", "/data/data/com.truecaller/shared_prefs/com.google.android.gms.appid.xml", "/data/data/com.truecaller/shared_prefs/com.truecaller_preferences.xml", "/data/data/com.truecaller/files/logs/debug.log", "/data/data/com.truecaller/shared_prefs/gcm-scheduler-engine-initial.xml", "/data/data/com.truecaller/shared_prefs/com.facebook.sdk.appEventPreferences.xml", "/data/data/com.truecaller/shared_prefs/com.facebook.sdk.attributionTracking.xml", "/data/data/com.truecaller/files/persisted_config", "/data/data/com.truecaller/shared_prefs/com.crashlytics.prefs.xml", "/data/data/com.truecaller/shared_prefs/TwitterAdvertisingInfoPreferences.xml", "/data/data/com.truecaller/files/.Fabric/com.crashlytics.sdk.android.crashlytics-core/56849AFB0243-0001-3CAA-9CCC36733B72BeginSession.cls_temp", "/data/data/com.truecaller/files/AppEventsLogger.persistedevents", "/data/data/com.truecaller/files/.Fabric/com.crashlytics.sdk.android.crashlytics-core/56849AFB0243-0001-3CAA-9CCC36733B72BeginSession.json", "/data/data/com.truecaller/files/.Fabric/com.crashlytics.sdk.android.crashlytics-core/56849AFB0243-0001-3CAA-9CCC36733B72SessionApp.cls_temp", "/data/data/com.truecaller/files/.Fabric/com.crashlytics.sdk.android:answers/session_analytics.tap.tmp", "/data/data/com.truecaller/files/.Fabric/com.crashlytics.sdk.android:answers/session_analytics.tap", "/data/data/com.truecaller/files/.Fabric/com.crashlytics.sdk.android.crashlytics-core/56849AFB0243-0001-3CAA-9CCC36733B72SessionApp.json", "/data/data/com.truecaller/files/.Fabric/com.crashlytics.sdk.android.crashlytics-core/56849AFB0243-0001-3CAA-9CCC36733B72SessionOS.cls_temp", "/data/data/com.truecaller/files/.Fabric/com.crashlytics.sdk.android.crashlytics-core/56849AFB0243-0001-3CAA-9CCC36733B72SessionOS.json", "/data/data/com.truecaller/files/.Fabric/com.crashlytics.sdk.android:answers/session_analytics_to_send/sa_41fec7c0-e468-415d-a600-dfb7cf88d66c_1451531007329.tap", "/data/data/com.truecaller/files/.Fabric/com.crashlytics.sdk.android.crashlytics-core/56849AFB0243-0001-3CAA-9CCC36733B72SessionDevice.cls_temp", "/data/data/com.truecaller/files/.Fabric/com.crashlytics.sdk.android.crashlytics-core/56849AFB0243-0001-3CAA-9CCC36733B72SessionDevice.json", "/data/data/com.truecaller/files/.Fabric/com.crashlytics.sdk.android.crashlytics-core/56849AFB0243-0001-3CAA-9CCC36733B72keys.meta", "/data/data/com.truecaller/cache/disklru/journal.tmp", "/data/data/com.truecaller/files/.Fabric/com.crashlytics.sdk.android.crashlytics-core/56849AFB0243-0001-3CAA-9CCC36733B72user.meta", "/data/data/com.truecaller/files/.Fabric/com.crashlytics.sdk.android.crashlytics-core/56849AFB0243-0001-3CAA-9CCC36733B72SessionEvent0000000000.cls_temp", "/data/data/com.truecaller/files/.Fabric/com.crashlytics.sdk.android.crashlytics-core/56849AFB0243-0001-3CAA-9CCC36733B72SessionEvent0000000001.cls_temp", "/data/data/com.truecaller/files/.Fabric/com.crashlytics.sdk.android.crashlytics-core/56849AFD00DD-0001-3CAD-EF6F5D39AFE1BeginSession.cls_temp", "/data/data/com.truecaller/files/.Fabric/com.crashlytics.sdk.android.crashlytics-core/56849AFD00DD-0001-3CAD-EF6F5D39AFE1BeginSession.json", "/data/data/com.truecaller/files/.Fabric/com.crashlytics.sdk.android:answers/session_analytics_to_send/sa_a3bc1fd2-34b8-4902-94ec-db5130c509a6_1451531008862.tap", "/data/data/com.truecaller/files/.Fabric/com.crashlytics.sdk.android.crashlytics-core/56849AFD00DD-0001-3CAD-EF6F5D39AFE1SessionApp.cls_temp", "/data/data/com.truecaller/files/.Fabric/com.crashlytics.sdk.android.crashlytics-core/56849AFD00DD-0001-3CAD-EF6F5D39AFE1SessionApp.json", "/data/data/com.truecaller/files/.Fabric/com.crashlytics.sdk.android.crashlytics-core/56849AFD00DD-0001-3CAD-EF6F5D39AFE1SessionOS.cls_temp", "/data/data/com.truecaller/files/.Fabric/com.crashlytics.sdk.android.crashlytics-core/56849AFD00DD-0001-3CAD-EF6F5D39AFE1SessionOS.json", "/data/data/com.truecaller/files/.Fabric/com.crashlytics.sdk.android.crashlytics-core/56849AFD00DD-0001-3CAD-EF6F5D39AFE1SessionDevice.cls_temp", "/data/data/com.truecaller/files/.Fabric/com.crashlytics.sdk.android.crashlytics-core/56849AFD00DD-0001-3CAD-EF6F5D39AFE1SessionDevice.json", "/data/data/com.truecaller/files/.Fabric/com.crashlytics.sdk.android.crashlytics-core/56849AFD00DD-0001-3CAD-EF6F5D39AFE1keys.meta", "/data/data/com.truecaller/files/.Fabric/com.crashlytics.sdk.android.crashlytics-core/56849AFD00DD-0001-3CAD-EF6F5D39AFE1user.meta", "/data/data/com.truecaller/files/.Fabric/com.crashlytics.sdk.android.crashlytics-core/56849AFD00DD-0001-3CAD-EF6F5D39AFE1SessionEvent0000000000.cls_temp", "/data/data/com.truecaller/files/.Fabric/com.crashlytics.sdk.android.crashlytics-core/56849AFD00DD-0001-3CAD-EF6F5D39AFE1SessionEvent0000000001.cls_temp", "/data/data/com.truecaller/code_cache/secondary-dexes/tmp-com.truecaller-1.apk.classes1748197113.zip", "/data/data/com.truecaller/code_cache/secondary-dexes/tmp-com.truecaller-1.apk.classes705844626.zip", "/data/data/com.truecaller/no_backup/com.google.android.gms.appid-no-backup", "/data/data/com.truecaller/no_backup/com.google.InstanceId.properties", "/data/data/com.truecaller/code_cache/secondary-dexes/tmp-com.truecaller-1.apk.classes1043513851.zip", "/data/data/com.truecaller/code_cache/secondary-dexes/tmp-com.truecaller-1.apk.classes-1358075736.zip", "/data/data/com.truecaller/code_cache/secondary-dexes/tmp-com.truecaller-1.apk.classes-9718566.zip", "/data/data/com.truecaller/code_cache/secondary-dexes/tmp-com.truecaller-1.apk.classes-336909264.zip", "/data/data/com.truecaller/code_cache/secondary-dexes/tmp-com.truecaller-1.apk.classes200446278.zip", "/data/data/com.truecaller/code_cache/secondary-dexes/tmp-com.truecaller-1.apk.classes1158926755.zip", "/data/data/com.truecaller/code_cache/secondary-dexes/tmp-com.truecaller-1.apk.classes349206185.zip", "/data/data/com.truecaller/code_cache/secondary-dexes/tmp-com.truecaller-1.apk.classes1265145320.zip", "/data/data/com.truecaller/code_cache/secondary-dexes/tmp-com.truecaller-1.apk.classes973863240.zip", "/data/data/com.truecaller/code_cache/secondary-dexes/tmp-com.truecaller-1.apk.classes-1395577478.zip", "/data/data/com.truecaller/code_cache/secondary-dexes/tmp-com.truecaller-1.apk.classes554949328.zip", "/data/data/com.truecaller/code_cache/secondary-dexes/tmp-com.truecaller-1.apk.classes-889815587.zip", "/data/data/com.truecaller/code_cache/secondary-dexes/tmp-com.truecaller-1.apk.classes77493471.zip", "/data/data/com.truecaller/code_cache/secondary-dexes/tmp-com.truecaller-1.apk.classes-1341913348.zip", "/data/data/com.truecaller/code_cache/secondary-dexes/tmp-com.truecaller-1.apk.classes2010398187.zip", "/data/data/com.truecaller/code_cache/secondary-dexes/tmp-com.truecaller-1.apk.classes-305569047.zip"], "system_property_lookups": ["debug.force_rtl", "persist.sys.timezone"], "dns_lookups": [{"resolved_ips": ["185.60.216.15"], "hostname": "graph.facebook.com"}, {"resolved_ips": ["185.60.216.15"], "hostname": "star.c10r.facebook.com"}, {"resolved_ips": ["179.60.195.7"], "hostname": "graph.facebook.com"}, {"resolved_ips": ["179.60.195.7"], "hostname": "star.c10r.facebook.com"}, {"resolved_ips": ["179.60.192.3"], "hostname": "graph.facebook.com"}, {"resolved_ips": ["179.60.192.3"], "hostname": "star.c10r.facebook.com"}, {"resolved_ips": ["157.240.21.16"], "hostname": "graph.facebook.com"}, {"resolved_ips": ["157.240.21.16"], "hostname": "star.c10r.facebook.com"}], "files_dropped": [{"sha256": "4b2fb7850959685fc25994081bfa9205c7807618524e0e4b3a78b602895463bf"}, {"sha256": "50095a614cd938107e1f8496458a234fcba75eb93ef5c77fb2ccf43a6652b2b4"}, {"sha256": "7b8a98cce6af2549e7a3cfc055128dc8254c3a855c7938a92c63a1e1e4e38c28"}, {"sha256": "4fccc91e4ef28b674cb5869f352d49b3febe327dba84303f73936ef30cfa3b0c"}], "command_executions": ["su"], "services_started": ["com.truecaller/com.truecaller.service.CallStateService", "com.truecaller/com.truecaller.service.ClipboardService", "com.truecaller/com.truecaller.service.RefreshT9MappingService", "com.truecaller/com.truecaller.common.tag.TagService", "com.truecaller/com.truecaller.presence.PresenceService", "com.truecaller/com.truecaller.analytics.EventsTrackerService", "com.truecaller/com.truecaller.callerid.CallerIdService"], "services_opened": ["com.google.android.finsky.services.ContentSyncService (com.android.vending)", "com.google.android.gms.app.service.PackageBroadcastService (com.google.android.gms)", "com.google.android.gms.games.service.GamesIntentService (com.google.android.gms)", "com.google.android.gms.icing.service.LightweightIndexService (com.google.process.gapps)", "com.google.android.gms.icing.service.IndexWorkerService (com.google.android.gms)", "com.google.android.partnersetup.RlzPingIntentService (com.google.android.partnersetup)", "com.google.android.gms.people.service.bg.PeopleBackgroundTasks (com.google.android.gms)", "com.google.android.syncadapters.contacts.ContactsSyncAdapterService (com.google.process.gapps)"], "http_conversations": [{"url": "https://graph.facebook.com/v2.11/126694440681943?fields=supports_implicit_sdk_logging%2Cgdpv4_nux_content%2Cgdpv4_nux_enabled%2Cgdpv4_chrome_custom_tabs_enabled%2Candroid_dialog_configs%2Candroid_sdk_error_categories%2Capp_events_session_timeout%2Capp_events_feature_bitmask%2Cseamless_login%2Csmart_login_bookmark_icon_url%2Csmart_login_menu_icon_url&format=json&sdk=android", "request_method": "GET", "response_status_code": 200}]}}